Workbook

Sheet 总览
A1: PIMART 内部库存价格管理
A2: 当前汇率（CNY→JPY） | B2: =系统设置!$C$5 | D2: 网站 | E2: https://pimart-card-production.up.railway.app/?game=pokemon
A3: 更新日期 | B3: 2026-07-07 23:19 | D3: 使用说明：日常在「宝可梦 / 海贼王 / 火影」分页改【库存】+【销售价(JPY)】；「全量库存」自动汇总。汇率和阈值改「系统设置」一次生效。
A5: 核心指标
A6: 库存总金额(JPY) | D6: P0 紧急调价
A7: 在售 SKU | D7: P1 售罄/低毛利
A8: 售罄 SKU | D8: P2 需要补货
A9: 低库存 SKU | D9: 海贼王 SKU 数 | E9: =COUNTIFS(全量库存!$AB$5:$AB$500,"One Piece")
A10: 需要调价 SKU
A11: 汇率风险 SKU
A12: 平均毛利率
A13: 建议补货 SKU
A15: ① 需要调价
A16: 商品名 | B16: 当前售价 | C16: 建议售价 | D16: 毛利率 | E16: 调价建议
A28: ② 低库存
A29: 商品名 | B29: 当前库存 | C29: 预警线 | D29: 库存变化
A41: ③ 汇率风险
A42: 商品名 | B42: 成本CNY | C42: 入货汇率 | D42: 当前汇率 | E42: 汇率差 | F42: 建议
A54: 说明：修改「当前汇率」后全表自动重算；成本价(CNY)/成本汇率为手工录入；#NAME? 已改为带引号工作表引用。

Sheet 系统设置
A1: 系统设置 · 参数中心
A2: 说明：改这里的参数，「总览」「全量库存」全表自动重算；日常只需要在「全量库存」里维护「库存」和「销售价(JPY)」两列。
A4: 汇率设置
A5: 当前汇率（CNY→JPY） | B5: 与「总览」互相联动，改这里两边同步；原数值未改动 | C5: 21.8
A6: 人民币→日元（自动）
A8: 毛利率阈值（原写死在「全量库存」公式里，现集中到这里）
A9: 利润过低阈值 | B9: 毛利率低于此值 → 价格状态标「利润过低」，调价建议「建议涨价」 | C9: 0.1
A10: 目标毛利率 | B10: 毛利率达到此值 → 「利润正常/维持」；也用于反推「建议售价」（售价=成本/(1-目标毛利率)） | C10: 0.2
A12: 风险与库存阈值
A13: 汇率风险阈值 | B13: 汇率差率超过此值 → 标记「汇率风险」 | C13: 0.05
A14: 默认库存预警线 | B14: 参考值；现有商品「全量库存」里已各自设置预警线，此项不覆盖 | C14: 3
A16: 系统信息
A17: 系统名称 | C17: PIMART 内部库存价格管理
A18: 最后更新

Sheet 宝可梦
A1: 宝可梦 · PIMART
A2: 【大纲 1 / 2】点「1」只显示原盒主行（日常改库存/售价）。点「2」或行号旁「+」展开散包/原箱（有规格的新品写到这一层）。新品：先写规格=原盒，再在下方挂散包、原箱两行。
A3: 商品名 | B3: 系列 | C3: 盒型/类型 | D3: 规格 | E3: 销售状态 | F3: 库存 | G3: 销售价(JPY) | H3: 成本价(CNY) | I3: 语言 | J3: 是否预售 | K3: 首页推荐 | L3: 发货天数 | M3: 图片 | N3: 优先级 | O3: 商品类型 | P3: 备注 | Q3: 商品ID | R3: SKU/Slug | S3: 游戏 | T3: 商品链接
A4: 朱・紫 · 扩充包（瘦盒优先 / 新→旧）
A5: 第10弹 · 共逐荣光（瘦盒5张装 / 肥盒20张装）
A6: 补充包 共逐荣光 瘦盒 BOX（简中） | B6: 朱・紫 CSV10c | C6: 瘦盒 | D6: 原盒 | E6: 售罄 | F6: 0 | G6: 6500 | H6: 170 | I6: 简中 | J6: 是 | K6: 是 | L6: 5 | M6: /products/csv10c-slim.png | O6: 扩充包 | P6: 官网/集换社：朱&紫「共逐荣光」同弹分肥瘦。本行=瘦盒（5张装×15包/盒）。配对另一规格见同弹另一行。 | 参考：官网/集换社：同弹肥瘦配对。本行=肥盒（20张装×6包/盒）。 | 朱紫第10弹，2026-07-16发售。含222+张卡牌，全新「训练家的宝可梦」卡牌类型，5张装10元/包，20张装50元/包。 | Q6: c6a43bce026a4cc8a76523 | R6: 共逐荣光-简中-slim-box-简中 | S6: Pokemon | T6: https://pimart-card-production.up.railway.app/products/共逐荣光-box-简中
A7: 补充包 共逐荣光 瘦盒 BOX（简中） | B7: 朱・紫 CSV10c | C7: 瘦盒 | D7: 散包 | E7: 售罄 | H7: 170 | I7: 简中 | J7: 是 | K7: 是 | L7: 5 | M7: /products/csv10c-slim.png | O7: 扩充包 | P7: 官网/集换社：朱&紫「共逐荣光」同弹分肥瘦。本行=瘦盒（5张装×15包/盒）。配对另一规格见同弹另一行。 | 参考：官网/集换社：同弹肥瘦配对。本行=肥盒（20张装×6包/盒）。 | 朱紫第10弹，2026-07-16发售。含222+张卡牌，全新「训练家的宝可梦」卡牌类型，5张装10元/包，20张装50元/包。 | Q7: c6a43bce026a4cc8a76523 | R7: 共逐荣光-简中-slim-box-简中 | S7: Pokemon | T7: https://pimart-card-production.up.railway.app/products/共逐荣光-box-简中
A8: 补充包 共逐荣光 瘦盒 BOX（简中） | B8: 朱・紫 CSV10c | C8: 瘦盒 | D8: 原箱 | E8: 售罄 | H8: 170 | I8: 简中 | J8: 是 | K8: 是 | L8: 5 | M8: /products/csv10c-slim.png | O8: 扩充包 | P8: 官网/集换社：朱&紫「共逐荣光」同弹分肥瘦。本行=瘦盒（5张装×15包/盒）。配对另一规格见同弹另一行。 | 参考：官网/集换社：同弹肥瘦配对。本行=肥盒（20张装×6包/盒）。 | 朱紫第10弹，2026-07-16发售。含222+张卡牌，全新「训练家的宝可梦」卡牌类型，5张装10元/包，20张装50元/包。 | Q8: c6a43bce026a4cc8a76523 | R8: 共逐荣光-简中-slim-box-简中 | S8: Pokemon | T8: https://pimart-card-production.up.railway.app/products/共逐荣光-box-简中
A9: 补充包 共逐荣光 肥盒 BOX（简中） | B9: 朱・紫 CSV10c | C9: 肥盒 | D9: 原盒 | E9: 预售 | F9: 0 | G9: 6500 | H9: 170 | I9: 简中 | J9: 是 | K9: 是 | L9: 5 | M9: /products/csv10c-fat.png | O9: 扩充包 | P9: 官网/集换社：同弹肥瘦配对。本行=肥盒（20张装×6包/盒）。 | 朱紫第10弹，2026-07-16发售。含222+张卡牌，全新「训练家的宝可梦」卡牌类型，5张装10元/包，20张装50元/包。 | Q9: c6a43bce026a4cc8a76523 | R9: 共逐荣光-fat-box-简中 | S9: Pokemon | T9: https://pimart-card-production.up.railway.app/products/共逐荣光-box-简中
A10: 补充包 共逐荣光 肥盒 BOX（简中） | B10: 朱・紫 CSV10c | C10: 肥盒 | D10: 散包 | E10: 预售 | H10: 170 | I10: 简中 | J10: 是 | K10: 是 | L10: 5 | M10: /products/csv10c-fat.png | O10: 扩充包 | P10: 官网/集换社：同弹肥瘦配对。本行=肥盒（20张装×6包/盒）。 | 朱紫第10弹，2026-07-16发售。含222+张卡牌，全新「训练家的宝可梦」卡牌类型，5张装10元/包，20张装50元/包。 | Q10: c6a43bce026a4cc8a76523 | R10: 共逐荣光-fat-box-简中 | S10: Pokemon | T10: https://pimart-card-production.up.railway.app/products/共逐荣光-box-简中
A11: 补充包 共逐荣光 肥盒 BOX（简中） | B11: 朱・紫 CSV10c | C11: 肥盒 | D11: 原箱 | E11: 预售 | H11: 170 | I11: 简中 | J11: 是 | K11: 是 | L11: 5 | M11: /products/csv10c-fat.png | O11: 扩充包 | P11: 官网/集换社：同弹肥瘦配对。本行=肥盒（20张装×6包/盒）。 | 朱紫第10弹，2026-07-16发售。含222+张卡牌，全新「训练家的宝可梦」卡牌类型，5张装10元/包，20张装50元/包。 | Q11: c6a43bce026a4cc8a76523 | R11: 共逐荣光-fat-box-简中 | S11: Pokemon | T11: https://pimart-card-production.up.railway.app/products/共逐荣光-box-简中
A12: 第9弹 · 星彩晶璃（瘦盒5张装 / 肥盒20张装）
A13: 补充包 星彩晶璃 瘦盒 BOX（简中） | B13: 朱・紫 CSV9c | C13: 瘦盒 | D13: 原盒 | E13: 售罄 | F13: 0 | G13: 6200 | H13: 166.34 | I13: 简中 | J13: 否 | K13: 是 | L13: 6 | M13: /products/csv9c-slim.png | O13: 扩充包 | P13: 官网/集换社：朱&紫「星彩晶璃」同弹分肥瘦。本行=瘦盒（5张装×15包/盒）。配对另一规格见同弹另一行。 | 参考：官网/集换社：同弹肥瘦配对。本行=肥盒（20张装×6包/盒）。 | 简中宝可梦 朱・紫 星彩晶璃（Stellar Crown）原盒，2026年4月24日发售。每盒含10包，每包含5张卡牌，必出闪卡。 | Q13: a4af2b9b-e2da-4400-b3cc-3063a0892551 | R13: 星彩晶璃-简中-slim-box-简中 | S13: Pokemon | T13: https://pimart-card-production.up.railway.app/products/%E6%98%9F%E5%BD%A9%E6%99%B6%E7%92%83-box-%E7%AE%80%E4%B8%AD
A14: 补充包 星彩晶璃 瘦盒 BOX（简中） | B14: 朱・紫 CSV9c | C14: 瘦盒 | D14: 散包 | E14: 售罄 | H14: 166.34 | I14: 简中 | J14: 否 | K14: 是 | L14: 6 | M14: /products/csv9c-slim.png | O14: 扩充包 | P14: 官网/集换社：朱&紫「星彩晶璃」同弹分肥瘦。本行=瘦盒（5张装×15包/盒）。配对另一规格见同弹另一行。 | 参考：官网/集换社：同弹肥瘦配对。本行=肥盒（20张装×6包/盒）。 | 简中宝可梦 朱・紫 星彩晶璃（Stellar Crown）原盒，2026年4月24日发售。每盒含10包，每包含5张卡牌，必出闪卡。 | Q14: a4af2b9b-e2da-4400-b3cc-3063a0892551 | R14: 星彩晶璃-简中-slim-box-简中 | S14: Pokemon | T14: https://pimart-card-production.up.railway.app/products/%E6%98%9F%E5%BD%A9%E6%99%B6%E7%92%83-box-%E7%AE%80%E4%B8%AD
A15: 补充包 星彩晶璃 瘦盒 BOX（简中） | B15: 朱・紫 CSV9c | C15: 瘦盒 | D15: 原箱 | E15: 售罄 | H15: 166.34 | I15: 简中 | J15: 否 | K15: 是 | L15: 6 | M15: /products/csv9c-slim.png | O15: 扩充包 | P15: 官网/集换社：朱&紫「星彩晶璃」同弹分肥瘦。本行=瘦盒（5张装×15包/盒）。配对另一规格见同弹另一行。 | 参考：官网/集换社：同弹肥瘦配对。本行=肥盒（20张装×6包/盒）。 | 简中宝可梦 朱・紫 星彩晶璃（Stellar Crown）原盒，2026年4月24日发售。每盒含10包，每包含5张卡牌，必出闪卡。 | Q15: a4af2b9b-e2da-4400-b3cc-3063a0892551 | R15: 星彩晶璃-简中-slim-box-简中 | S15: Pokemon | T15: https://pimart-card-production.up.railway.app/products/%E6%98%9F%E5%BD%A9%E6%99%B6%E7%92%83-box-%E7%AE%80%E4%B8%AD
A16: 补充包 星彩晶璃 肥盒 BOX（简中） | B16: 朱・紫 CSV9c | C16: 肥盒 | D16: 原盒 | E16: 在售 | F16: 20 | G16: 6200 | H16: 166.34 | I16: 简中 | J16: 否 | K16: 是 | L16: 6 | M16: /products/csv9c-fat.png | O16: 扩充包 | P16: 官网/集换社：同弹肥瘦配对。本行=肥盒（20张装×6包/盒）。 | 简中宝可梦 朱・紫 星彩晶璃（Stellar Crown）原盒，2026年4月24日发售。每盒含10包，每包含5张卡牌，必出闪卡。 | Q16: a4af2b9b-e2da-4400-b3cc-3063a0892551 | R16: 星彩晶璃-fat-box-简中 | S16: Pokemon | T16: https://pimart-card-production.up.railway.app/products/%E6%98%9F%E5%BD%A9%E6%99%B6%E7%92%83-box-%E7%AE%80%E4%B8%AD
A17: 补充包 星彩晶璃 肥盒 BOX（简中） | B17: 朱・紫 CSV9c | C17: 肥盒 | D17: 散包 | E17: 在售 | H17: 166.34 | I17: 简中 | J17: 否 | K17: 是 | L17: 6 | M17: /products/csv9c-fat.png | O17: 扩充包 | P17: 官网/集换社：同弹肥瘦配对。本行=肥盒（20张装×6包/盒）。 | 简中宝可梦 朱・紫 星彩晶璃（Stellar Crown）原盒，2026年4月24日发售。每盒含10包，每包含5张卡牌，必出闪卡。 | Q17: a4af2b9b-e2da-4400-b3cc-3063a0892551 | R17: 星彩晶璃-fat-box-简中 | S17: Pokemon | T17: https://pimart-card-production.up.railway.app/products/%E6%98%9F%E5%BD%A9%E6%99%B6%E7%92%83-box-%E7%AE%80%E4%B8%AD
A18: 补充包 星彩晶璃 肥盒 BOX（简中） | B18: 朱・紫 CSV9c | C18: 肥盒 | D18: 原箱 | E18: 在售 | H18: 166.34 | I18: 简中 | J18: 否 | K18: 是 | L18: 6 | M18: /products/csv9c-fat.png | O18: 扩充包 | P18: 官网/集换社：同弹肥瘦配对。本行=肥盒（20张装×6包/盒）。 | 简中宝可梦 朱・紫 星彩晶璃（Stellar Crown）原盒，2026年4月24日发售。每盒含10包，每包含5张卡牌，必出闪卡。 | Q18: a4af2b9b-e2da-4400-b3cc-3063a0892551 | R18: 星彩晶璃-fat-box-简中 | S18: Pokemon | T18: https://pimart-card-production.up.railway.app/products/%E6%98%9F%E5%BD%A9%E6%99%B6%E7%92%83-box-%E7%AE%80%E4%B8%AD
A19: 第8弹 · 璀璨诡幻（瘦盒5张装 / 肥盒20张装）
A20: 补充包 璀璨诡幻 瘦盒 BOX（简中） | B20: 朱・紫 CSV8c | C20: 瘦盒 | D20: 原盒 | E20: 售罄 | F20: 0 | G20: 6000 | H20: 160.98 | I20: 简中 | J20: 否 | K20: 否 | L20: 6 | M20: /products/csv8c-slim.png | O20: 扩充包 | P20: 官网/集换社：同弹肥瘦配对。本行=瘦盒（5张装×15包/盒）。 | 简中宝可梦 朱&紫 璀璨诡幻（CSV8C）原盒，2026年3月13日发售，每盒30包，每包5张。 | Q20: cmqui01q100044odkmmm85re4 | R20: 璀璨诡幻-slim-box-简中 | S20: Pokemon | T20: https://pimart-card-production.up.railway.app/products/%E7%92%80%E7%92%A8%E8%AF%A1%E5%B9%BB-box-%E7%AE%80%E4%B8%AD
A21: 补充包 璀璨诡幻 瘦盒 BOX（简中） | B21: 朱・紫 CSV8c | C21: 瘦盒 | D21: 散包 | E21: 售罄 | H21: 160.98 | I21: 简中 | J21: 否 | K21: 否 | L21: 6 | M21: /products/csv8c-slim.png | O21: 扩充包 | P21: 官网/集换社：同弹肥瘦配对。本行=瘦盒（5张装×15包/盒）。 | 简中宝可梦 朱&紫 璀璨诡幻（CSV8C）原盒，2026年3月13日发售，每盒30包，每包5张。 | Q21: cmqui01q100044odkmmm85re4 | R21: 璀璨诡幻-slim-box-简中 | S21: Pokemon | T21: https://pimart-card-production.up.railway.app/products/%E7%92%80%E7%92%A8%E8%AF%A1%E5%B9%BB-box-%E7%AE%80%E4%B8%AD
A22: 补充包 璀璨诡幻 瘦盒 BOX（简中） | B22: 朱・紫 CSV8c | C22: 瘦盒 | D22: 原箱 | E22: 售罄 | H22: 160.98 | I22: 简中 | J22: 否 | K22: 否 | L22: 6 | M22: /products/csv8c-slim.png | O22: 扩充包 | P22: 官网/集换社：同弹肥瘦配对。本行=瘦盒（5张装×15包/盒）。 | 简中宝可梦 朱&紫 璀璨诡幻（CSV8C）原盒，2026年3月13日发售，每盒30包，每包5张。 | Q22: cmqui01q100044odkmmm85re4 | R22: 璀璨诡幻-slim-box-简中 | S22: Pokemon | T22: https://pimart-card-production.up.railway.app/products/%E7%92%80%E7%92%A8%E8%AF%A1%E5%B9%BB-box-%E7%AE%80%E4%B8%AD
A23: 补充包 璀璨诡幻 肥盒 BOX（简中） | B23: 朱・紫 CSV8c | C23: 肥盒 | D23: 原盒 | E23: 售罄 | F23: 0 | G23: 6000 | H23: 160.98 | I23: 简中 | J23: 否 | K23: 否 | L23: 6 | M23: /products/csv8c-fat.png | O23: 扩充包 | P23: 官网/集换社：朱&紫「璀璨诡幻」同弹分肥瘦。本行=肥盒（20张装×6包/盒）。配对另一规格见同弹另一行。 | 参考：官网/集换社：同弹肥瘦配对。本行=瘦盒（5张装×15包/盒）。 | 简中宝可梦 朱&紫 璀璨诡幻（CSV8C）原盒，2026年3月13日发售，每盒30包，每包5张。 | Q23: cmqui01q100044odkmmm85re4 | R23: 璀璨诡幻-简中-fat-box-简中 | S23: Pokemon | T23: https://pimart-card-production.up.railway.app/products/%E7%92%80%E7%92%A8%E8%AF%A1%E5%B9%BB-box-%E7%AE%80%E4%B8%AD
A24: 补充包 璀璨诡幻 肥盒 BOX（简中） | B24: 朱・紫 CSV8c | C24: 肥盒 | D24: 散包 | E24: 售罄 | H24: 160.98 | I24: 简中 | J24: 否 | K24: 否 | L24: 6 | M24: /products/csv8c-fat.png | O24: 扩充包 | P24: 官网/集换社：朱&紫「璀璨诡幻」同弹分肥瘦。本行=肥盒（20张装×6包/盒）。配对另一规格见同弹另一行。 | 参考：官网/集换社：同弹肥瘦配对。本行=瘦盒（5张装×15包/盒）。 | 简中宝可梦 朱&紫 璀璨诡幻（CSV8C）原盒，2026年3月13日发售，每盒30包，每包5张。 | Q24: cmqui01q100044odkmmm85re4 | R24: 璀璨诡幻-简中-fat-box-简中 | S24: Pokemon | T24: https://pimart-card-production.up.railway.app/products/%E7%92%80%E7%92%A8%E8%AF%A1%E5%B9%BB-box-%E7%AE%80%E4%B8%AD
A25: 补充包 璀璨诡幻 肥盒 BOX（简中） | B25: 朱・紫 CSV8c | C25: 肥盒 | D25: 原箱 | E25: 售罄 | H25: 160.98 | I25: 简中 | J25: 否 | K25: 否 | L25: 6 | M25: /products/csv8c-fat.png | O25: 扩充包 | P25: 官网/集换社：朱&紫「璀璨诡幻」同弹分肥瘦。本行=肥盒（20张装×6包/盒）。配对另一规格见同弹另一行。 | 参考：官网/集换社：同弹肥瘦配对。本行=瘦盒（5张装×15包/盒）。 | 简中宝可梦 朱&紫 璀璨诡幻（CSV8C）原盒，2026年3月13日发售，每盒30包，每包5张。 | Q25: cmqui01q100044odkmmm85re4 | R25: 璀璨诡幻-简中-fat-box-简中 | S25: Pokemon | T25: https://pimart-card-production.up.railway.app/products/%E7%92%80%E7%92%A8%E8%AF%A1%E5%B9%BB-box-%E7%AE%80%E4%B8%AD
A26: 第7弹 · 利刃猛醒（瘦盒5张装 / 肥盒20张装）
A27: 补充包 利刃猛醒 瘦盒 BOX（简中） | B27: 朱・紫 CSV7c | C27: 瘦盒 | D27: 原盒 | E27: 售罄 | F27: 0 | G27: 5800 | H27: 155.61 | I27: 简中 | J27: 否 | K27: 否 | L27: 6 | M27: /products/csv7c-slim.png | O27: 扩充包 | P27: 官网/集换社：朱&紫「利刃猛醒」同弹分肥瘦。本行=瘦盒（5张装×15包/盒）。配对另一规格见同弹另一行。 | 参考：官网/集换社：同弹肥瘦配对。本行=肥盒（20张装×6包/盒）。 | 简中宝可梦 朱・紫 剑刃觉醒（Blade Awakening）原盒，现货发售。 | Q27: 470d321e-88ab-4e61-bcb9-94fa1ff06d18 | R27: 剑刃觉醒-简中-slim-box-简中 | S27: Pokemon | T27: https://pimart-card-production.up.railway.app/products/%E5%89%91%E5%88%83%E8%A7%89%E9%86%92-box-%E7%AE%80%E4%B8%AD
A28: 补充包 利刃猛醒 瘦盒 BOX（简中） | B28: 朱・紫 CSV7c | C28: 瘦盒 | D28: 散包 | E28: 售罄 | H28: 155.61 | I28: 简中 | J28: 否 | K28: 否 | L28: 6 | M28: /products/csv7c-slim.png | O28: 扩充包 | P28: 官网/集换社：朱&紫「利刃猛醒」同弹分肥瘦。本行=瘦盒（5张装×15包/盒）。配对另一规格见同弹另一行。 | 参考：官网/集换社：同弹肥瘦配对。本行=肥盒（20张装×6包/盒）。 | 简中宝可梦 朱・紫 剑刃觉醒（Blade Awakening）原盒，现货发售。 | Q28: 470d321e-88ab-4e61-bcb9-94fa1ff06d18 | R28: 剑刃觉醒-简中-slim-box-简中 | S28: Pokemon | T28: https://pimart-card-production.up.railway.app/products/%E5%89%91%E5%88%83%E8%A7%89%E9%86%92-box-%E7%AE%80%E4%B8%AD
A29: 补充包 利刃猛醒 瘦盒 BOX（简中） | B29: 朱・紫 CSV7c | C29: 瘦盒 | D29: 原箱 | E29: 售罄 | H29: 155.61 | I29: 简中 | J29: 否 | K29: 否 | L29: 6 | M29: /products/csv7c-slim.png | O29: 扩充包 | P29: 官网/集换社：朱&紫「利刃猛醒」同弹分肥瘦。本行=瘦盒（5张装×15包/盒）。配对另一规格见同弹另一行。 | 参考：官网/集换社：同弹肥瘦配对。本行=肥盒（20张装×6包/盒）。 | 简中宝可梦 朱・紫 剑刃觉醒（Blade Awakening）原盒，现货发售。 | Q29: 470d321e-88ab-4e61-bcb9-94fa1ff06d18 | R29: 剑刃觉醒-简中-slim-box-简中 | S29: Pokemon | T29: https://pimart-card-production.up.railway.app/products/%E5%89%91%E5%88%83%E8%A7%89%E9%86%92-box-%E7%AE%80%E4%B8%AD
A30: 补充包 利刃猛醒 肥盒 BOX（简中） | B30: 朱・紫 CSV7c | C30: 肥盒 | D30: 原盒 | E30: 在售 | F30: 18 | G30: 5800 | H30: 155.61 | I30: 简中 | J30: 否 | K30: 否 | L30: 6 | M30: /products/csv7c-fat.png | O30: 扩充包 | P30: 官网/集换社：同弹肥瘦配对。本行=肥盒（20张装×6包/盒）。 | 简中宝可梦 朱・紫 剑刃觉醒（Blade Awakening）原盒，现货发售。 | Q30: 470d321e-88ab-4e61-bcb9-94fa1ff06d18 | R30: 剑刃觉醒-fat-box-简中 | S30: Pokemon | T30: https://pimart-card-production.up.railway.app/products/%E5%89%91%E5%88%83%E8%A7%89%E9%86%92-box-%E7%AE%80%E4%B8%AD
A31: 补充包 利刃猛醒 肥盒 BOX（简中） | B31: 朱・紫 CSV7c | C31: 肥盒 | D31: 散包 | E31: 在售 | H31: 155.61 | I31: 简中 | J31: 否 | K31: 否 | L31: 6 | M31: /products/csv7c-fat.png | O31: 扩充包 | P31: 官网/集换社：同弹肥瘦配对。本行=肥盒（20张装×6包/盒）。 | 简中宝可梦 朱・紫 剑刃觉醒（Blade Awakening）原盒，现货发售。 | Q31: 470d321e-88ab-4e61-bcb9-94fa1ff06d18 | R31: 剑刃觉醒-fat-box-简中 | S31: Pokemon | T31: https://pimart-card-production.up.railway.app/products/%E5%89%91%E5%88%83%E8%A7%89%E9%86%92-box-%E7%AE%80%E4%B8%AD
A32: 补充包 利刃猛醒 肥盒 BOX（简中） | B32: 朱・紫 CSV7c | C32: 肥盒 | D32: 原箱 | E32: 在售 | H32: 155.61 | I32: 简中 | J32: 否 | K32: 否 | L32: 6 | M32: /products/csv7c-fat.png | O32: 扩充包 | P32: 官网/集换社：同弹肥瘦配对。本行=肥盒（20张装×6包/盒）。 | 简中宝可梦 朱・紫 剑刃觉醒（Blade Awakening）原盒，现货发售。 | Q32: 470d321e-88ab-4e61-bcb9-94fa1ff06d18 | R32: 剑刃觉醒-fat-box-简中 | S32: Pokemon | T32: https://pimart-card-production.up.railway.app/products/%E5%89%91%E5%88%83%E8%A7%89%E9%86%92-box-%E7%AE%80%E4%B8%AD
A33: 第6弹 · 真实玄虚（瘦盒5张装 / 肥盒20张装）
A34: 补充包 真实玄虚 瘦盒 BOX（简中） | B34: 朱・紫 CSV6c | C34: 瘦盒 | D34: 原盒 | E34: 售罄 | F34: 0 | G34: 5600 | H34: 150.24 | I34: 简中 | J34: 否 | K34: 否 | L34: 6 | M34: /products/csv6c-slim.png | O34: 扩充包 | P34: 官网/集换社：同弹肥瘦配对。本行=瘦盒（5张装×15包/盒）。 | 简中宝可梦 朱&紫 真实玄虚（CSV6C）原盒，2025年11月7日发售，每盒30包，每包5张。 | Q34: cmqui01pw00034odkfh4woe8g | R34: 真实玄虚-slim-box-简中 | S34: Pokemon | T34: https://pimart-card-production.up.railway.app/products/%E7%9C%9F%E5%AE%9E%E7%8E%84%E8%99%9A-box-%E7%AE%80%E4%B8%AD
A35: 补充包 真实玄虚 瘦盒 BOX（简中） | B35: 朱・紫 CSV6c | C35: 瘦盒 | D35: 散包 | E35: 售罄 | H35: 150.24 | I35: 简中 | J35: 否 | K35: 否 | L35: 6 | M35: /products/csv6c-slim.png | O35: 扩充包 | P35: 官网/集换社：同弹肥瘦配对。本行=瘦盒（5张装×15包/盒）。 | 简中宝可梦 朱&紫 真实玄虚（CSV6C）原盒，2025年11月7日发售，每盒30包，每包5张。 | Q35: cmqui01pw00034odkfh4woe8g | R35: 真实玄虚-slim-box-简中 | S35: Pokemon | T35: https://pimart-card-production.up.railway.app/products/%E7%9C%9F%E5%AE%9E%E7%8E%84%E8%99%9A-box-%E7%AE%80%E4%B8%AD
A36: 补充包 真实玄虚 瘦盒 BOX（简中） | B36: 朱・紫 CSV6c | C36: 瘦盒 | D36: 原箱 | E36: 售罄 | H36: 150.24 | I36: 简中 | J36: 否 | K36: 否 | L36: 6 | M36: /products/csv6c-slim.png | O36: 扩充包 | P36: 官网/集换社：同弹肥瘦配对。本行=瘦盒（5张装×15包/盒）。 | 简中宝可梦 朱&紫 真实玄虚（CSV6C）原盒，2025年11月7日发售，每盒30包，每包5张。 | Q36: cmqui01pw00034odkfh4woe8g | R36: 真实玄虚-slim-box-简中 | S36: Pokemon | T36: https://pimart-card-production.up.railway.app/products/%E7%9C%9F%E5%AE%9E%E7%8E%84%E8%99%9A-box-%E7%AE%80%E4%B8%AD
A37: 补充包 真实玄虚 肥盒 BOX（简中） | B37: 朱・紫 CSV6c | C37: 肥盒 | D37: 原盒 | E37: 售罄 | F37: 0 | G37: 5600 | H37: 150.24 | I37: 简中 | J37: 否 | K37: 否 | L37: 6 | M37: /products/csv6c-fat.png | O37: 扩充包 | P37: 官网/集换社：朱&紫「真实玄虚」同弹分肥瘦。本行=肥盒（20张装×6包/盒）。配对另一规格见同弹另一行。 | 参考：官网/集换社：同弹肥瘦配对。本行=瘦盒（5张装×15包/盒）。 | 简中宝可梦 朱&紫 真实玄虚（CSV6C）原盒，2025年11月7日发售，每盒30包，每包5张。 | Q37: cmqui01pw00034odkfh4woe8g | R37: 真实玄虚-简中-fat-box-简中 | S37: Pokemon | T37: https://pimart-card-production.up.railway.app/products/%E7%9C%9F%E5%AE%9E%E7%8E%84%E8%99%9A-box-%E7%AE%80%E4%B8%AD
A38: 补充包 真实玄虚 肥盒 BOX（简中） | B38: 朱・紫 CSV6c | C38: 肥盒 | D38: 散包 | E38: 售罄 | H38: 150.24 | I38: 简中 | J38: 否 | K38: 否 | L38: 6 | M38: /products/csv6c-fat.png | O38: 扩充包 | P38: 官网/集换社：朱&紫「真实玄虚」同弹分肥瘦。本行=肥盒（20张装×6包/盒）。配对另一规格见同弹另一行。 | 参考：官网/集换社：同弹肥瘦配对。本行=瘦盒（5张装×15包/盒）。 | 简中宝可梦 朱&紫 真实玄虚（CSV6C）原盒，2025年11月7日发售，每盒30包，每包5张。 | Q38: cmqui01pw00034odkfh4woe8g | R38: 真实玄虚-简中-fat-box-简中 | S38: Pokemon | T38: https://pimart-card-production.up.railway.app/products/%E7%9C%9F%E5%AE%9E%E7%8E%84%E8%99%9A-box-%E7%AE%80%E4%B8%AD
A39: 补充包 真实玄虚 肥盒 BOX（简中） | B39: 朱・紫 CSV6c | C39: 肥盒 | D39: 原箱 | E39: 售罄 | H39: 150.24 | I39: 简中 | J39: 否 | K39: 否 | L39: 6 | M39: /products/csv6c-fat.png | O39: 扩充包 | P39: 官网/集换社：朱&紫「真实玄虚」同弹分肥瘦。本行=肥盒（20张装×6包/盒）。配对另一规格见同弹另一行。 | 参考：官网/集换社：同弹肥瘦配对。本行=瘦盒（5张装×15包/盒）。 | 简中宝可梦 朱&紫 真实玄虚（CSV6C）原盒，2025年11月7日发售，每盒30包，每包5张。 | Q39: cmqui01pw00034odkfh4woe8g | R39: 真实玄虚-简中-fat-box-简中 | S39: Pokemon | T39: https://pimart-card-production.up.railway.app/products/%E7%9C%9F%E5%AE%9E%E7%8E%84%E8%99%9A-box-%E7%AE%80%E4%B8%AD
A40: 第5弹 · 黑晶炽诚（瘦盒5张装 / 肥盒20张装）
A41: 补充包 黑晶炽诚 瘦盒 BOX（简中） | B41: 朱・紫 CSV5c | C41: 瘦盒 | D41: 原盒 | E41: 售罄 | F41: 0 | G41: 5500 | H41: 147.56 | I41: 简中 | J41: 否 | K41: 否 | L41: 6 | M41: /products/csv5c-slim.png | O41: 扩充包 | P41: 官网/集换社：朱&紫「黑晶炽诚」同弹分肥瘦。本行=瘦盒（5张装×15包/盒）。配对另一规格见同弹另一行。 | 参考：官网/集换社：同弹肥瘦配对。本行=肥盒（20张装×6包/盒）。 | 简中宝可梦 朱・紫 黑晶炽焰（Black Crystal Blaze）原盒，现货发售。 | Q41: c1fc8f48-9440-4ea9-94be-d58b04bd5884 | R41: 黑晶炽焰-简中-slim-box-简中 | S41: Pokemon | T41: https://pimart-card-production.up.railway.app/products/%E9%BB%91%E6%99%B6%E7%82%BD%E7%84%B0-box-%E7%AE%80%E4%B8%AD
A42: 补充包 黑晶炽诚 瘦盒 BOX（简中） | B42: 朱・紫 CSV5c | C42: 瘦盒 | D42: 散包 | E42: 售罄 | H42: 147.56 | I42: 简中 | J42: 否 | K42: 否 | L42: 6 | M42: /products/csv5c-slim.png | O42: 扩充包 | P42: 官网/集换社：朱&紫「黑晶炽诚」同弹分肥瘦。本行=瘦盒（5张装×15包/盒）。配对另一规格见同弹另一行。 | 参考：官网/集换社：同弹肥瘦配对。本行=肥盒（20张装×6包/盒）。 | 简中宝可梦 朱・紫 黑晶炽焰（Black Crystal Blaze）原盒，现货发售。 | Q42: c1fc8f48-9440-4ea9-94be-d58b04bd5884 | R42: 黑晶炽焰-简中-slim-box-简中 | S42: Pokemon | T42: https://pimart-card-production.up.railway.app/products/%E9%BB%91%E6%99%B6%E7%82%BD%E7%84%B0-box-%E7%AE%80%E4%B8%AD
A43: 补充包 黑晶炽诚 瘦盒 BOX（简中） | B43: 朱・紫 CSV5c | C43: 瘦盒 | D43: 原箱 | E43: 售罄 | H43: 147.56 | I43: 简中 | J43: 否 | K43: 否 | L43: 6 | M43: /products/csv5c-slim.png | O43: 扩充包 | P43: 官网/集换社：朱&紫「黑晶炽诚」同弹分肥瘦。本行=瘦盒（5张装×15包/盒）。配对另一规格见同弹另一行。 | 参考：官网/集换社：同弹肥瘦配对。本行=肥盒（20张装×6包/盒）。 | 简中宝可梦 朱・紫 黑晶炽焰（Black Crystal Blaze）原盒，现货发售。 | Q43: c1fc8f48-9440-4ea9-94be-d58b04bd5884 | R43: 黑晶炽焰-简中-slim-box-简中 | S43: Pokemon | T43: https://pimart-card-production.up.railway.app/products/%E9%BB%91%E6%99%B6%E7%82%BD%E7%84%B0-box-%E7%AE%80%E4%B8%AD
A44: 补充包 黑晶炽诚 肥盒 BOX（简中） | B44: 朱・紫 CSV5c | C44: 肥盒 | D44: 原盒 | E44: 在售 | F44: 15 | G44: 5500 | H44: 147.56 | I44: 简中 | J44: 否 | K44: 否 | L44: 6 | M44: /products/csv5c-fat.png | O44: 扩充包 | P44: 官网/集换社：同弹肥瘦配对。本行=肥盒（20张装×6包/盒）。 | 简中宝可梦 朱・紫 黑晶炽焰（Black Crystal Blaze）原盒，现货发售。 | Q44: c1fc8f48-9440-4ea9-94be-d58b04bd5884 | R44: 黑晶炽焰-fat-box-简中 | S44: Pokemon | T44: https://pimart-card-production.up.railway.app/products/%E9%BB%91%E6%99%B6%E7%82%BD%E7%84%B0-box-%E7%AE%80%E4%B8%AD
A45: 补充包 黑晶炽诚 肥盒 BOX（简中） | B45: 朱・紫 CSV5c | C45: 肥盒 | D45: 散包 | E45: 在售 | H45: 147.56 | I45: 简中 | J45: 否 | K45: 否 | L45: 6 | M45: /products/csv5c-fat.png | O45: 扩充包 | P45: 官网/集换社：同弹肥瘦配对。本行=肥盒（20张装×6包/盒）。 | 简中宝可梦 朱・紫 黑晶炽焰（Black Crystal Blaze）原盒，现货发售。 | Q45: c1fc8f48-9440-4ea9-94be-d58b04bd5884 | R45: 黑晶炽焰-fat-box-简中 | S45: Pokemon | T45: https://pimart-card-production.up.railway.app/products/%E9%BB%91%E6%99%B6%E7%82%BD%E7%84%B0-box-%E7%AE%80%E4%B8%AD
A46: 补充包 黑晶炽诚 肥盒 BOX（简中） | B46: 朱・紫 CSV5c | C46: 肥盒 | D46: 原箱 | E46: 在售 | H46: 147.56 | I46: 简中 | J46: 否 | K46: 否 | L46: 6 | M46: /products/csv5c-fat.png | O46: 扩充包 | P46: 官网/集换社：同弹肥瘦配对。本行=肥盒（20张装×6包/盒）。 | 简中宝可梦 朱・紫 黑晶炽焰（Black Crystal Blaze）原盒，现货发售。 | Q46: c1fc8f48-9440-4ea9-94be-d58b04bd5884 | R46: 黑晶炽焰-fat-box-简中 | S46: Pokemon | T46: https://pimart-card-production.up.railway.app/products/%E9%BB%91%E6%99%B6%E7%82%BD%E7%84%B0-box-%E7%AE%80%E4%B8%AD
A47: 第4弹 · 嘉奖回合（瘦盒5张装 / 肥盒20张装）
A48: 补充包 嘉奖回合 瘦盒 BOX（简中） | B48: 朱・紫 CSV4c | C48: 瘦盒 | D48: 原盒 | E48: 售罄 | F48: 0 | G48: 5200 | H48: 139.51 | I48: 简中 | J48: 否 | K48: 否 | L48: 6 | M48: /products/csv4c-slim.png | O48: 扩充包 | P48: 官网/集换社：同弹肥瘦配对。本行=瘦盒（5张装×15包/盒）。 | 简中宝可梦 朱&紫 嘉奖回合（CSV4C）原盒，2025年7月18日发售，每盒30包，每包5张。 | Q48: cmqui01pr00024odkpyf93vhq | R48: 嘉奖回合-slim-box-简中 | S48: Pokemon | T48: https://pimart-card-production.up.railway.app/products/%E5%98%89%E5%A5%96%E5%9B%9E%E5%90%88-box-%E7%AE%80%E4%B8%AD
A49: 补充包 嘉奖回合 瘦盒 BOX（简中） | B49: 朱・紫 CSV4c | C49: 瘦盒 | D49: 散包 | E49: 售罄 | H49: 139.51 | I49: 简中 | J49: 否 | K49: 否 | L49: 6 | M49: /products/csv4c-slim.png | O49: 扩充包 | P49: 官网/集换社：同弹肥瘦配对。本行=瘦盒（5张装×15包/盒）。 | 简中宝可梦 朱&紫 嘉奖回合（CSV4C）原盒，2025年7月18日发售，每盒30包，每包5张。 | Q49: cmqui01pr00024odkpyf93vhq | R49: 嘉奖回合-slim-box-简中 | S49: Pokemon | T49: https://pimart-card-production.up.railway.app/products/%E5%98%89%E5%A5%96%E5%9B%9E%E5%90%88-box-%E7%AE%80%E4%B8%AD
A50: 补充包 嘉奖回合 瘦盒 BOX（简中） | B50: 朱・紫 CSV4c | C50: 瘦盒 | D50: 原箱 | E50: 售罄 | H50: 139.51 | I50: 简中 | J50: 否 | K50: 否 | L50: 6 | M50: /products/csv4c-slim.png | O50: 扩充包 | P50: 官网/集换社：同弹肥瘦配对。本行=瘦盒（5张装×15包/盒）。 | 简中宝可梦 朱&紫 嘉奖回合（CSV4C）原盒，2025年7月18日发售，每盒30包，每包5张。 | Q50: cmqui01pr00024odkpyf93vhq | R50: 嘉奖回合-slim-box-简中 | S50: Pokemon | T50: https://pimart-card-production.up.railway.app/products/%E5%98%89%E5%A5%96%E5%9B%9E%E5%90%88-box-%E7%AE%80%E4%B8%AD
A51: 补充包 嘉奖回合 肥盒 BOX（简中） | B51: 朱・紫 CSV4c | C51: 肥盒 | D51: 原盒 | E51: 售罄 | F51: 0 | G51: 5200 | H51: 139.51 | I51: 简中 | J51: 否 | K51: 否 | L51: 6 | M51: /products/csv4c-fat.png | O51: 扩充包 | P51: 官网/集换社：朱&紫「嘉奖回合」同弹分肥瘦。本行=肥盒（20张装×6包/盒）。配对另一规格见同弹另一行。 | 参考：官网/集换社：同弹肥瘦配对。本行=瘦盒（5张装×15包/盒）。 | 简中宝可梦 朱&紫 嘉奖回合（CSV4C）原盒，2025年7月18日发售，每盒30包，每包5张。 | Q51: cmqui01pr00024odkpyf93vhq | R51: 嘉奖回合-简中-fat-box-简中 | S51: Pokemon | T51: https://pimart-card-production.up.railway.app/products/%E5%98%89%E5%A5%96%E5%9B%9E%E5%90%88-box-%E7%AE%80%E4%B8%AD
A52: 补充包 嘉奖回合 肥盒 BOX（简中） | B52: 朱・紫 CSV4c | C52: 肥盒 | D52: 散包 | E52: 售罄 | H52: 139.51 | I52: 简中 | J52: 否 | K52: 否 | L52: 6 | M52: /products/csv4c-fat.png | O52: 扩充包 | P52: 官网/集换社：朱&紫「嘉奖回合」同弹分肥瘦。本行=肥盒（20张装×6包/盒）。配对另一规格见同弹另一行。 | 参考：官网/集换社：同弹肥瘦配对。本行=瘦盒（5张装×15包/盒）。 | 简中宝可梦 朱&紫 嘉奖回合（CSV4C）原盒，2025年7月18日发售，每盒30包，每包5张。 | Q52: cmqui01pr00024odkpyf93vhq | R52: 嘉奖回合-简中-fat-box-简中 | S52: Pokemon | T52: https://pimart-card-production.up.railway.app/products/%E5%98%89%E5%A5%96%E5%9B%9E%E5%90%88-box-%E7%AE%80%E4%B8%AD
A53: 补充包 嘉奖回合 肥盒 BOX（简中） | B53: 朱・紫 CSV4c | C53: 肥盒 | D53: 原箱 | E53: 售罄 | H53: 139.51 | I53: 简中 | J53: 否 | K53: 否 | L53: 6 | M53: /products/csv4c-fat.png | O53: 扩充包 | P53: 官网/集换社：朱&紫「嘉奖回合」同弹分肥瘦。本行=肥盒（20张装×6包/盒）。配对另一规格见同弹另一行。 | 参考：官网/集换社：同弹肥瘦配对。本行=瘦盒（5张装×15包/盒）。 | 简中宝可梦 朱&紫 嘉奖回合（CSV4C）原盒，2025年7月18日发售，每盒30包，每包5张。 | Q53: cmqui01pr00024odkpyf93vhq | R53: 嘉奖回合-简中-fat-box-简中 | S53: Pokemon | T53: https://pimart-card-production.up.railway.app/products/%E5%98%89%E5%A5%96%E5%9B%9E%E5%90%88-box-%E7%AE%80%E4%B8%AD
A54: 第3弹 · 无畏太晶（瘦盒5张装 / 肥盒20张装）
A55: 补充包 无畏太晶 瘦盒 BOX（简中） | B55: 朱・紫 CSV3c | C55: 瘦盒 | D55: 原盒 | E55: 售罄 | F55: 0 | G55: 5000 | H55: 134.15 | I55: 简中 | J55: 否 | K55: 否 | L55: 6 | M55: /products/csv3c-slim.png | O55: 扩充包 | P55: 官网/集换社：同弹肥瘦配对。本行=瘦盒（5张装×15包/盒）。 | 简中宝可梦 朱&紫 无畏太晶（CSV3C）原盒，2025年5月16日发售，每盒30包，每包5张。 | Q55: cmqui01pm00014odkjaq7ee1t | R55: 无畏太晶-slim-box-简中 | S55: Pokemon | T55: https://pimart-card-production.up.railway.app/products/%E6%97%A0%E7%95%8F%E5%A4%AA%E6%99%B6-box-%E7%AE%80%E4%B8%AD
A56: 补充包 无畏太晶 瘦盒 BOX（简中） | B56: 朱・紫 CSV3c | C56: 瘦盒 | D56: 散包 | E56: 售罄 | H56: 134.15 | I56: 简中 | J56: 否 | K56: 否 | L56: 6 | M56: /products/csv3c-slim.png | O56: 扩充包 | P56: 官网/集换社：同弹肥瘦配对。本行=瘦盒（5张装×15包/盒）。 | 简中宝可梦 朱&紫 无畏太晶（CSV3C）原盒，2025年5月16日发售，每盒30包，每包5张。 | Q56: cmqui01pm00014odkjaq7ee1t | R56: 无畏太晶-slim-box-简中 | S56: Pokemon | T56: https://pimart-card-production.up.railway.app/products/%E6%97%A0%E7%95%8F%E5%A4%AA%E6%99%B6-box-%E7%AE%80%E4%B8%AD
A57: 补充包 无畏太晶 瘦盒 BOX（简中） | B57: 朱・紫 CSV3c | C57: 瘦盒 | D57: 原箱 | E57: 售罄 | H57: 134.15 | I57: 简中 | J57: 否 | K57: 否 | L57: 6 | M57: /products/csv3c-slim.png | O57: 扩充包 | P57: 官网/集换社：同弹肥瘦配对。本行=瘦盒（5张装×15包/盒）。 | 简中宝可梦 朱&紫 无畏太晶（CSV3C）原盒，2025年5月16日发售，每盒30包，每包5张。 | Q57: cmqui01pm00014odkjaq7ee1t | R57: 无畏太晶-slim-box-简中 | S57: Pokemon | T57: https://pimart-card-production.up.railway.app/products/%E6%97%A0%E7%95%8F%E5%A4%AA%E6%99%B6-box-%E7%AE%80%E4%B8%AD
A58: 补充包 无畏太晶 肥盒 BOX（简中） | B58: 朱・紫 CSV3c | C58: 肥盒 | D58: 原盒 | E58: 售罄 | F58: 0 | G58: 5000 | H58: 134.15 | I58: 简中 | J58: 否 | K58: 否 | L58: 6 | M58: /products/csv3c-fat.png | O58: 扩充包 | P58: 官网/集换社：朱&紫「无畏太晶」同弹分肥瘦。本行=肥盒（20张装×6包/盒）。配对另一规格见同弹另一行。 | 参考：官网/集换社：同弹肥瘦配对。本行=瘦盒（5张装×15包/盒）。 | 简中宝可梦 朱&紫 无畏太晶（CSV3C）原盒，2025年5月16日发售，每盒30包，每包5张。 | Q58: cmqui01pm00014odkjaq7ee1t | R58: 无畏太晶-简中-fat-box-简中 | S58: Pokemon | T58: https://pimart-card-production.up.railway.app/products/%E6%97%A0%E7%95%8F%E5%A4%AA%E6%99%B6-box-%E7%AE%80%E4%B8%AD
A59: 补充包 无畏太晶 肥盒 BOX（简中） | B59: 朱・紫 CSV3c | C59: 肥盒 | D59: 散包 | E59: 售罄 | H59: 134.15 | I59: 简中 | J59: 否 | K59: 否 | L59: 6 | M59: /products/csv3c-fat.png | O59: 扩充包 | P59: 官网/集换社：朱&紫「无畏太晶」同弹分肥瘦。本行=肥盒（20张装×6包/盒）。配对另一规格见同弹另一行。 | 参考：官网/集换社：同弹肥瘦配对。本行=瘦盒（5张装×15包/盒）。 | 简中宝可梦 朱&紫 无畏太晶（CSV3C）原盒，2025年5月16日发售，每盒30包，每包5张。 | Q59: cmqui01pm00014odkjaq7ee1t | R59: 无畏太晶-简中-fat-box-简中 | S59: Pokemon | T59: https://pimart-card-production.up.railway.app/products/%E6%97%A0%E7%95%8F%E5%A4%AA%E6%99%B6-box-%E7%AE%80%E4%B8%AD
A60: 补充包 无畏太晶 肥盒 BOX（简中） | B60: 朱・紫 CSV3c | C60: 肥盒 | D60: 原箱 | E60: 售罄 | H60: 134.15 | I60: 简中 | J60: 否 | K60: 否 | L60: 6 | M60: /products/csv3c-fat.png | O60: 扩充包 | P60: 官网/集换社：朱&紫「无畏太晶」同弹分肥瘦。本行=肥盒（20张装×6包/盒）。配对另一规格见同弹另一行。 | 参考：官网/集换社：同弹肥瘦配对。本行=瘦盒（5张装×15包/盒）。 | 简中宝可梦 朱&紫 无畏太晶（CSV3C）原盒，2025年5月16日发售，每盒30包，每包5张。 | Q60: cmqui01pm00014odkjaq7ee1t | R60: 无畏太晶-简中-fat-box-简中 | S60: Pokemon | T60: https://pimart-card-production.up.railway.app/products/%E6%97%A0%E7%95%8F%E5%A4%AA%E6%99%B6-box-%E7%AE%80%E4%B8%AD
A61: 第2弹 · 奇迹启程（瘦盒5张装 / 肥盒20张装）
A62: 补充包 奇迹启程 瘦盒 BOX（简中） | B62: 朱・紫 CSV2c | C62: 瘦盒 | D62: 原盒 | E62: 售罄 | F62: 0 | G62: 4800 | H62: 128.78 | I62: 简中 | J62: 否 | K62: 否 | L62: 6 | M62: /products/csv2c-slim.png | O62: 扩充包 | P62: 官网/集换社：同弹肥瘦配对。本行=瘦盒（5张装×15包/盒）。 | 简中宝可梦 朱&紫 奇迹启程（CSV2C）原盒，2025年3月21日发售，每盒30包，每包5张。 | Q62: cmqui01pg00004odkn7nxt4d2 | R62: 奇迹启程-slim-box-简中 | S62: Pokemon | T62: https://pimart-card-production.up.railway.app/products/%E5%A5%87%E8%BF%B9%E5%90%AF%E7%A8%8B-box-%E7%AE%80%E4%B8%AD
A63: 补充包 奇迹启程 瘦盒 BOX（简中） | B63: 朱・紫 CSV2c | C63: 瘦盒 | D63: 散包 | E63: 售罄 | H63: 128.78 | I63: 简中 | J63: 否 | K63: 否 | L63: 6 | M63: /products/csv2c-slim.png | O63: 扩充包 | P63: 官网/集换社：同弹肥瘦配对。本行=瘦盒（5张装×15包/盒）。 | 简中宝可梦 朱&紫 奇迹启程（CSV2C）原盒，2025年3月21日发售，每盒30包，每包5张。 | Q63: cmqui01pg00004odkn7nxt4d2 | R63: 奇迹启程-slim-box-简中 | S63: Pokemon | T63: https://pimart-card-production.up.railway.app/products/%E5%A5%87%E8%BF%B9%E5%90%AF%E7%A8%8B-box-%E7%AE%80%E4%B8%AD
A64: 补充包 奇迹启程 瘦盒 BOX（简中） | B64: 朱・紫 CSV2c | C64: 瘦盒 | D64: 原箱 | E64: 售罄 | H64: 128.78 | I64: 简中 | J64: 否 | K64: 否 | L64: 6 | M64: /products/csv2c-slim.png | O64: 扩充包 | P64: 官网/集换社：同弹肥瘦配对。本行=瘦盒（5张装×15包/盒）。 | 简中宝可梦 朱&紫 奇迹启程（CSV2C）原盒，2025年3月21日发售，每盒30包，每包5张。 | Q64: cmqui01pg00004odkn7nxt4d2 | R64: 奇迹启程-slim-box-简中 | S64: Pokemon | T64: https://pimart-card-production.up.railway.app/products/%E5%A5%87%E8%BF%B9%E5%90%AF%E7%A8%8B-box-%E7%AE%80%E4%B8%AD
A65: 补充包 奇迹启程 肥盒 BOX（简中） | B65: 朱・紫 CSV2c | C65: 肥盒 | D65: 原盒 | E65: 售罄 | F65: 0 | G65: 4800 | H65: 128.78 | I65: 简中 | J65: 否 | K65: 否 | L65: 6 | M65: /products/csv2c-fat.png | O65: 扩充包 | P65: 官网/集换社：朱&紫「奇迹启程」同弹分肥瘦。本行=肥盒（20张装×6包/盒）。配对另一规格见同弹另一行。 | 参考：官网/集换社：同弹肥瘦配对。本行=瘦盒（5张装×15包/盒）。 | 简中宝可梦 朱&紫 奇迹启程（CSV2C）原盒，2025年3月21日发售，每盒30包，每包5张。 | Q65: cmqui01pg00004odkn7nxt4d2 | R65: 奇迹启程-简中-fat-box-简中 | S65: Pokemon | T65: https://pimart-card-production.up.railway.app/products/%E5%A5%87%E8%BF%B9%E5%90%AF%E7%A8%8B-box-%E7%AE%80%E4%B8%AD
A66: 补充包 奇迹启程 肥盒 BOX（简中） | B66: 朱・紫 CSV2c | C66: 肥盒 | D66: 散包 | E66: 售罄 | H66: 128.78 | I66: 简中 | J66: 否 | K66: 否 | L66: 6 | M66: /products/csv2c-fat.png | O66: 扩充包 | P66: 官网/集换社：朱&紫「奇迹启程」同弹分肥瘦。本行=肥盒（20张装×6包/盒）。配对另一规格见同弹另一行。 | 参考：官网/集换社：同弹肥瘦配对。本行=瘦盒（5张装×15包/盒）。 | 简中宝可梦 朱&紫 奇迹启程（CSV2C）原盒，2025年3月21日发售，每盒30包，每包5张。 | Q66: cmqui01pg00004odkn7nxt4d2 | R66: 奇迹启程-简中-fat-box-简中 | S66: Pokemon | T66: https://pimart-card-production.up.railway.app/products/%E5%A5%87%E8%BF%B9%E5%90%AF%E7%A8%8B-box-%E7%AE%80%E4%B8%AD
A67: 补充包 奇迹启程 肥盒 BOX（简中） | B67: 朱・紫 CSV2c | C67: 肥盒 | D67: 原箱 | E67: 售罄 | H67: 128.78 | I67: 简中 | J67: 否 | K67: 否 | L67: 6 | M67: /products/csv2c-fat.png | O67: 扩充包 | P67: 官网/集换社：朱&紫「奇迹启程」同弹分肥瘦。本行=肥盒（20张装×6包/盒）。配对另一规格见同弹另一行。 | 参考：官网/集换社：同弹肥瘦配对。本行=瘦盒（5张装×15包/盒）。 | 简中宝可梦 朱&紫 奇迹启程（CSV2C）原盒，2025年3月21日发售，每盒30包，每包5张。 | Q67: cmqui01pg00004odkn7nxt4d2 | R67: 奇迹启程-简中-fat-box-简中 | S67: Pokemon | T67: https://pimart-card-production.up.railway.app/products/%E5%A5%87%E8%BF%B9%E5%90%AF%E7%A8%8B-box-%E7%AE%80%E4%B8%AD
A69: 第1弹 · 亘古开来（瘦盒5张装 / 肥盒20张装）
A70: 补充包 亘古开来 瘦盒 BOX（简中） | B70: 朱・紫 CSV1c | C70: 瘦盒 | D70: 原盒 | E70: 售罄 | F70: 0 | G70: 0 | I70: 简中 | J70: 否 | K70: 否 | L70: 6 | M70: /products/csv1c-slim.png | O70: 扩充包 | P70: 朱&紫第一弹「亘古开来」（CSV1c），2025-01-17发售；可选瘦盒/肥盒/散包/原箱。 | R70: csv1c-slim-box-简中 | S70: Pokemon
A71: 补充包 亘古开来 瘦盒 BOX（简中） | B71: 朱・紫 CSV1c | C71: 瘦盒 | D71: 散包 | E71: 售罄 | F71: 0 | G71: 0 | I71: 简中 | J71: 否 | K71: 否 | L71: 6 | M71: /products/csv1c-slim.png | O71: 扩充包 | P71: 朱&紫第一弹「亘古开来」（CSV1c），2025-01-17发售；可选瘦盒/肥盒/散包/原箱。 | R71: csv1c-slim-pack-简中 | S71: Pokemon
A72: 补充包 亘古开来 瘦盒 BOX（简中） | B72: 朱・紫 CSV1c | C72: 瘦盒 | D72: 原箱 | E72: 售罄 | F72: 0 | G72: 0 | I72: 简中 | J72: 否 | K72: 否 | L72: 6 | M72: /products/csv1c-slim.png | O72: 扩充包 | P72: 朱&紫第一弹「亘古开来」（CSV1c），2025-01-17发售；可选瘦盒/肥盒/散包/原箱。 | R72: csv1c-slim-case-简中 | S72: Pokemon
A73: 补充包 亘古开来 肥盒 BOX（简中） | B73: 朱・紫 CSV1c | C73: 肥盒 | D73: 原盒 | E73: 售罄 | F73: 0 | G73: 0 | I73: 简中 | J73: 否 | K73: 否 | L73: 6 | M73: /products/csv1c-fat.png | O73: 扩充包 | P73: 朱&紫第一弹「亘古开来」（CSV1c），2025-01-17发售；可选瘦盒/肥盒/散包/原箱。 | R73: csv1c-fat-box-简中 | S73: Pokemon
A74: 补充包 亘古开来 肥盒 BOX（简中） | B74: 朱・紫 CSV1c | C74: 肥盒 | D74: 散包 | E74: 售罄 | F74: 0 | G74: 0 | I74: 简中 | J74: 否 | K74: 否 | L74: 6 | M74: /products/csv1c-fat.png | O74: 扩充包 | P74: 朱&紫第一弹「亘古开来」（CSV1c），2025-01-17发售；可选瘦盒/肥盒/散包/原箱。 | R74: csv1c-fat-pack-简中 | S74: Pokemon
A75: 补充包 亘古开来 肥盒 BOX（简中） | B75: 朱・紫 CSV1c | C75: 肥盒 | D75: 原箱 | E75: 售罄 | F75: 0 | G75: 0 | I75: 简中 | J75: 否 | K75: 否 | L75: 6 | M75: /products/csv1c-fat.png | O75: 扩充包 | P75: 朱&紫第一弹「亘古开来」（CSV1c），2025-01-17发售；可选瘦盒/肥盒/散包/原箱。 | R75: csv1c-fat-case-简中 | S75: Pokemon
A76: 朱・紫 · 礼盒 / 套装 / 周边
A77: N对战套装礼盒（简中） | B77: 朱・紫 CSV10c | C77: 礼盒 | D77: 原盒 | E77: 预售 | F77: 0 | G77: 8500 | H77: 310 | I77: 简中 | J77: 是 | K77: 否 | L77: 6 | M77: /products/csv10c-slim.png | O77: 礼盒 | P77: 2026-07-16发售，零售价390元。含共逐荣光补充包6包+N主题艺术卡套64张+对战周边配件。 | Q77: be35f8f92e5443d598b98d | R77: n-battle-box-简中 | S77: Pokemon | T77: https://pimart-card-production.up.railway.app/products/n-battle-box-简中
A78: 伊布套装礼盒（简中） | B78: 朱・紫 太晶盛聚 | C78: 礼盒 | D78: 原盒 | E78: 在售 | F78: 0 | G78: 8200 | H78: 310 | I78: 简中 | J78: 否 | K78: 否 | L78: 6 | M78: /products/eevee-gift-box.png | O78: 礼盒 | P78: 2026-05-25发售。含太晶盛聚补充包8包（10张装）+伊布进化主题收藏卡册+主题艺术卡套64张，零售价390元，共9款可选。 | Q78: c40333cd00c34215ba9850 | R78: eevee-gift-box-简中 | S78: Pokemon | T78: https://pimart-card-production.up.railway.app/products/eevee-gift-box-简中
A79: 大师战略卡组构筑套装 多龙巴鲁托ex（简中） | B79: 朱・紫 CSV10c | C79: 构筑套装 | D79: 原盒 | E79: 预售 | F79: 0 | G79: 8500 | H79: 310 | I79: 简中 | J79: 是 | K79: 否 | L79: 6 | M79: /products/csv10c-slim.png | O79: 套装 | P79: 2026-07-16发售，零售价390元。含多龙巴鲁托ex主题卡组60张+改造包15张+共逐荣光补充包4包(20张装)+卡套+周边配件。 | Q79: 1bce95fa937d4c049bfc77 | R79: master-deck-多龙巴鲁托ex-简中 | S79: Pokemon | T79: https://pimart-card-production.up.railway.app/products/master-deck-多龙巴鲁托ex-简中
A80: 大师战略卡组构筑套装 猛雷鼓ex（简中） | B80: 朱・紫 CSV10c | C80: 构筑套装 | D80: 原盒 | E80: 预售 | F80: 0 | G80: 8500 | H80: 310 | I80: 简中 | J80: 是 | K80: 否 | L80: 6 | M80: /products/csv10c-slim.png | O80: 套装 | P80: 2026-07-16发售，零售价390元。含猛雷鼓ex主题卡组60张+改造包15张+共逐荣光补充包4包(20张装)+卡套+周边配件。 | Q80: 275dcfaa8f9f481284bcd4 | R80: master-deck-猛雷鼓ex-简中 | S80: Pokemon | T80: https://pimart-card-production.up.railway.app/products/master-deck-猛雷鼓ex-简中
A81: 大师战略卡组构筑套装 赛富豪ex（简中） | B81: 朱・紫 CSV10c | C81: 构筑套装 | D81: 原盒 | E81: 预售 | F81: 0 | G81: 8500 | H81: 310 | I81: 简中 | J81: 是 | K81: 否 | L81: 6 | M81: /products/csv10c-slim.png | O81: 套装 | P81: 2026-07-16发售，零售价390元。含赛富豪ex主题卡组60张+改造包15张+共逐荣光补充包4包(20张装)+卡套+周边配件。 | Q81: b2bbb8897bfa4ba7aad352 | R81: master-deck-赛富豪ex-简中 | S81: Pokemon | T81: https://pimart-card-production.up.railway.app/products/master-deck-赛富豪ex-简中
A82: 宝可梦卡牌嗨皮组合（简中） | B82: 朱・紫 CSV10c | C82: 对战套装 | D82: 原盒 | E82: 预售 | F82: 0 | G82: 2000 | H82: 72 | I82: 简中 | J82: 是 | K82: 否 | L82: 6 | M82: /products/csv10c-slim.png | O82: 套装 | P82: 2026-07-16发售，零售价88元。含快龙ex/超梦ex/喷火驼/来悲粗茶4套60张卡组+嗨皮包7包+改造包+入门配件，适合新手。 | Q82: abb263eb1fef45b6afbba3 | R82: happy-combo-简中 | S82: Pokemon | T82: https://pimart-card-production.up.railway.app/products/happy-combo-简中
A83: 火箭队的宏图专属礼盒（简中） | B83: 朱・紫 CSV10c | C83: 专属礼盒 | D83: 原盒 | E83: 预售 | F83: 0 | G83: 8500 | H83: 310 | I83: 简中 | J83: 是 | K83: 否 | L83: 6 | M83: /products/csv10c-slim.png | O83: 礼盒 | P83: 2026-07-16发售。以火箭队「R」为主题，内含共逐荣光相关补充包及周边，具体内容待官方公布。 | Q83: 107629b3456f418aabf4af | R83: rocket-gang-special-box-简中 | S83: Pokemon | T83: https://pimart-card-production.up.railway.app/products/rocket-gang-special-box-简中
A84: 莉莉艾对战套装礼盒（简中） | B84: 朱・紫 CSV10c | C84: 礼盒 | D84: 原盒 | E84: 售罄 | M84: /products/csv10c-slim.png | O84: 礼盒 | P84: 2026-07-16发售，零售价390元。含共逐荣光补充包6包+莉莉艾主题艺术卡套64张+对战周边配件。 | Q84: 33ed6daaea51487f9dfec7 | R84: lillie-battle-box-简中 | S84: Pokemon | T84: https://pimart-card-production.up.railway.app/products/lillie-battle-box-简中
A85: 补充包 强化扩张包 朱紫ex BOX（简中） | B85: 朱・紫ex | C85: 强化扩张包 | D85: 原盒 | E85: 在售 | F85: 10 | G85: 3200 | H85: 85.85 | I85: 简中 | J85: 否 | K85: 是 | L85: 6 | M85: /products/csv1c-box.png | O85: 扩充包 | P85: 官网：朱&紫 强化扩张包（非某弹瘦盒配对，独立SKU）。 | 简中宝可梦卡牌游戏 朱・紫ex 强化扩展包原盒，现货发售。 | Q85: cmqtx5qy80000kwdkxlxvkqsb | R85: 朱-紫ex-強化拡張パック-box-简中 | S85: Pokemon | T85: https://pimart-card-production.up.railway.app/products/%E6%9C%B1-%E7%B4%ABex-%E5%BC%B7%E5%8C%96%E6%8B%A1%E5%BC%B5%E3%83%91%E3%83%83%E3%82%AF-box-%E7%AE%80%E4%B8%AD
A86: 补充包 强化扩张包 朱紫ex BOX（简中） | B86: 朱・紫ex | C86: 强化扩张包 | D86: 散包 | E86: 在售 | H86: 85.85 | I86: 简中 | J86: 否 | K86: 是 | L86: 6 | M86: /products/csv1c-box.png | O86: 扩充包 | P86: 官网：朱&紫 强化扩张包（非某弹瘦盒配对，独立SKU）。 | 简中宝可梦卡牌游戏 朱・紫ex 强化扩展包原盒，现货发售。 | Q86: cmqtx5qy80000kwdkxlxvkqsb | R86: 朱-紫ex-強化拡張パック-box-简中 | S86: Pokemon | T86: https://pimart-card-production.up.railway.app/products/%E6%9C%B1-%E7%B4%ABex-%E5%BC%B7%E5%8C%96%E6%8B%A1%E5%BC%B5%E3%83%91%E3%83%83%E3%82%AF-box-%E7%AE%80%E4%B8%AD
A87: 补充包 强化扩张包 朱紫ex BOX（简中） | B87: 朱・紫ex | C87: 强化扩张包 | D87: 原箱 | E87: 在售 | H87: 85.85 | I87: 简中 | J87: 否 | K87: 是 | L87: 6 | M87: /products/csv1c-box.png | O87: 扩充包 | P87: 官网：朱&紫 强化扩张包（非某弹瘦盒配对，独立SKU）。 | 简中宝可梦卡牌游戏 朱・紫ex 强化扩展包原盒，现货发售。 | Q87: cmqtx5qy80000kwdkxlxvkqsb | R87: 朱-紫ex-強化拡張パック-box-简中 | S87: Pokemon | T87: https://pimart-card-production.up.railway.app/products/%E6%9C%B1-%E7%B4%ABex-%E5%BC%B7%E5%8C%96%E6%8B%A1%E5%BC%B5%E3%83%91%E3%83%83%E3%82%AF-box-%E7%AE%80%E4%B8%AD
A88: 雪危险+泥土猛击 双包（简中） | B88: 朱・紫 | C88: 礼盒 | D88: 原盒 | E88: 预售 | F88: 15 | G88: 6800 | H88: 182.44 | I88: 简中 | J88: 是 | K88: 否 | L88: 7 | M88: /products/sv2-double-box.png | O88: 礼盒 | P88: 简中宝可梦 雪 Hazard + Clay Burst 双包套装，预售商品。 | Q88: cmqtx5qyy0004kwdkdyvdktz2 | R88: スノ-ハザ-ド-クレイバ-スト-ダブルパック-简中 | S88: Pokemon | T88: https://pimart-card-production.up.railway.app/products/%E3%82%B9%E3%83%8E-%E3%83%8F%E3%82%B6-%E3%83%89-%E3%82%AF%E3%83%AC%E3%82%A4%E3%83%90-%E3%82%B9%E3%83%88-%E3%83%80%E3%83%96%E3%83%AB%E3%83%91%E3%83%83%E3%82%AF-%E7%AE%80%E4%B8%AD
A89: 黑炎霸主 BOX（简中） | B89: 朱・紫 | C89: 礼盒 | D89: 原盒 | E89: 在售 | F89: 8 | G89: 4200 | H89: 112.68 | I89: 简中 | J89: 否 | K89: 否 | L89: 5 | M89: /products/sv3-box.png | O89: 礼盒 | P89: 简中宝可梦 朱・紫 黑炎的支配者原盒，现货发售。 | Q89: cmqtx5qys0003kwdk51e9rmsr | R89: 朱-紫-黒炎の支配者-box-简中 | S89: Pokemon | T89: https://pimart-card-production.up.railway.app/products/%E6%9C%B1-%E7%B4%AB-%E9%BB%92%E7%82%8E%E3%81%AE%E6%94%AF%E9%85%8D%E8%80%85-box-%E7%AE%80%E4%B8%AD
A91: 宝石包（独立系列）
A92: 宝石包第五弹 BOX（简中） | B92: 宝石包 | C92: 宝石包 | D92: 原盒 | E92: 在售 | F92: 10 | G92: 7800 | H92: 209.27 | I92: 简中 | J92: 否 | K92: 是 | L92: 6 | M92: /products/cbb5c-box.png | O92: 扩充包 | P92: 简中宝可梦 宝石包第五弹原盒，每包含4张卡牌均为闪卡，稀有度极高。 | Q92: 166f979a-f782-4c9d-860d-729930933cb8 | R92: 宝石包第五弹-box-简中 | S92: Pokemon | T92: https://pimart-card-production.up.railway.app/products/%E5%AE%9D%E7%9F%B3%E5%8C%85%E7%AC%AC%E4%BA%94%E5%BC%B9-box-%E7%AE%80%E4%B8%AD
A93: 宝石包第五弹 BOX（简中） | B93: 宝石包 | C93: 宝石包 | D93: 散包 | E93: 在售 | H93: 209.27 | I93: 简中 | J93: 否 | K93: 是 | L93: 6 | M93: /products/cbb5c-box.png | O93: 扩充包 | P93: 简中宝可梦 宝石包第五弹原盒，每包含4张卡牌均为闪卡，稀有度极高。 | Q93: 166f979a-f782-4c9d-860d-729930933cb8 | R93: 宝石包第五弹-box-简中 | S93: Pokemon | T93: https://pimart-card-production.up.railway.app/products/%E5%AE%9D%E7%9F%B3%E5%8C%85%E7%AC%AC%E4%BA%94%E5%BC%B9-box-%E7%AE%80%E4%B8%AD
A94: 宝石包第五弹 BOX（简中） | B94: 宝石包 | C94: 宝石包 | D94: 原箱 | E94: 在售 | H94: 209.27 | I94: 简中 | J94: 否 | K94: 是 | L94: 6 | M94: /products/cbb5c-box.png | O94: 扩充包 | P94: 简中宝可梦 宝石包第五弹原盒，每包含4张卡牌均为闪卡，稀有度极高。 | Q94: 166f979a-f782-4c9d-860d-729930933cb8 | R94: 宝石包第五弹-box-简中 | S94: Pokemon | T94: https://pimart-card-production.up.railway.app/products/%E5%AE%9D%E7%9F%B3%E5%8C%85%E7%AC%AC%E4%BA%94%E5%BC%B9-box-%E7%AE%80%E4%B8%AD
A95: 宝石包第四弹 BOX（简中） | B95: 宝石包 | C95: 宝石包 | D95: 原盒 | E95: 售罄 | F95: 0 | G95: 7600 | H95: 203.9 | I95: 简中 | J95: 否 | K95: 否 | L95: 6 | M95: /products/cbb4c-box.png | O95: 扩充包 | P95: 简中宝可梦 宝石包 第四弹（CBB4C）原盒，2026年2月6日发售，每盒15包，每包4张全闪。 | Q95: cmqui01ql00084odk47lih7a7 | R95: 宝石包第四弹-box-简中 | S95: Pokemon | T95: https://pimart-card-production.up.railway.app/products/%E5%AE%9D%E7%9F%B3%E5%8C%85%E7%AC%AC%E5%9B%9B%E5%BC%B9-box-%E7%AE%80%E4%B8%AD
A96: 宝石包第四弹 BOX（简中） | B96: 宝石包 | C96: 宝石包 | D96: 散包 | E96: 售罄 | H96: 203.9 | I96: 简中 | J96: 否 | K96: 否 | L96: 6 | M96: /products/cbb4c-box.png | O96: 扩充包 | P96: 简中宝可梦 宝石包 第四弹（CBB4C）原盒，2026年2月6日发售，每盒15包，每包4张全闪。 | Q96: cmqui01ql00084odk47lih7a7 | R96: 宝石包第四弹-box-简中 | S96: Pokemon | T96: https://pimart-card-production.up.railway.app/products/%E5%AE%9D%E7%9F%B3%E5%8C%85%E7%AC%AC%E5%9B%9B%E5%BC%B9-box-%E7%AE%80%E4%B8%AD
A97: 宝石包第四弹 BOX（简中） | B97: 宝石包 | C97: 宝石包 | D97: 原箱 | E97: 售罄 | H97: 203.9 | I97: 简中 | J97: 否 | K97: 否 | L97: 6 | M97: /products/cbb4c-box.png | O97: 扩充包 | P97: 简中宝可梦 宝石包 第四弹（CBB4C）原盒，2026年2月6日发售，每盒15包，每包4张全闪。 | Q97: cmqui01ql00084odk47lih7a7 | R97: 宝石包第四弹-box-简中 | S97: Pokemon | T97: https://pimart-card-production.up.railway.app/products/%E5%AE%9D%E7%9F%B3%E5%8C%85%E7%AC%AC%E5%9B%9B%E5%BC%B9-box-%E7%AE%80%E4%B8%AD
A98: 宝石包第三弹 BOX（简中） | B98: 宝石包 | C98: 宝石包 | D98: 原盒 | E98: 售罄 | F98: 0 | G98: 8000 | H98: 214.63 | I98: 简中 | J98: 否 | K98: 否 | L98: 6 | M98: /products/cbb3c-box.png | O98: 扩充包 | P98: 简中宝可梦 宝石包 第三弹（CBB3C）原盒，2025年9月26日发售，每盒15包，每包4张全闪。 | Q98: cmqui01qf00074odks1y9i3ki | R98: 宝石包第三弹-box-简中 | S98: Pokemon | T98: https://pimart-card-production.up.railway.app/products/%E5%AE%9D%E7%9F%B3%E5%8C%85%E7%AC%AC%E4%B8%89%E5%BC%B9-box-%E7%AE%80%E4%B8%AD
A99: 宝石包第三弹 BOX（简中） | B99: 宝石包 | C99: 宝石包 | D99: 散包 | E99: 售罄 | H99: 214.63 | I99: 简中 | J99: 否 | K99: 否 | L99: 6 | M99: /products/cbb3c-box.png | O99: 扩充包 | P99: 简中宝可梦 宝石包 第三弹（CBB3C）原盒，2025年9月26日发售，每盒15包，每包4张全闪。 | Q99: cmqui01qf00074odks1y9i3ki | R99: 宝石包第三弹-box-简中 | S99: Pokemon | T99: https://pimart-card-production.up.railway.app/products/%E5%AE%9D%E7%9F%B3%E5%8C%85%E7%AC%AC%E4%B8%89%E5%BC%B9-box-%E7%AE%80%E4%B8%AD
A100: 宝石包第三弹 BOX（简中） | B100: 宝石包 | C100: 宝石包 | D100: 原箱 | E100: 售罄 | H100: 214.63 | I100: 简中 | J100: 否 | K100: 否 | L100: 6 | M100: /products/cbb3c-box.png | O100: 扩充包 | P100: 简中宝可梦 宝石包 第三弹（CBB3C）原盒，2025年9月26日发售，每盒15包，每包4张全闪。 | Q100: cmqui01qf00074odks1y9i3ki | R100: 宝石包第三弹-box-简中 | S100: Pokemon | T100: https://pimart-card-production.up.railway.app/products/%E5%AE%9D%E7%9F%B3%E5%8C%85%E7%AC%AC%E4%B8%89%E5%BC%B9-box-%E7%AE%80%E4%B8%AD
A101: 宝石包第二弹 BOX（简中） | B101: 宝石包 | C101: 宝石包 | D101: 原盒 | E101: 售罄 | F101: 0 | M101: /products/cbb2c-box.png | O101: 扩充包 | P101: 简中宝可梦 宝石包 第二弹（CBB2C）原盒，2025年5月16日发售，每盒15包，每包4张全闪。 | Q101: cmqui01qa00064odkgs2402lt | R101: 宝石包第二弹-box-简中 | S101: Pokemon | T101: https://pimart-card-production.up.railway.app/products/%E5%AE%9D%E7%9F%B3%E5%8C%85%E7%AC%AC%E4%BA%8C%E5%BC%B9-box-%E7%AE%80%E4%B8%AD
A102: 宝石包第二弹 BOX（简中） | B102: 宝石包 | C102: 宝石包 | D102: 散包 | E102: 售罄 | F102: 0 | M102: /products/cbb2c-box.png | O102: 扩充包 | P102: 简中宝可梦 宝石包 第二弹（CBB2C）原盒，2025年5月16日发售，每盒15包，每包4张全闪。 | Q102: cmqui01qa00064odkgs2402lt | R102: 宝石包第二弹-box-简中 | S102: Pokemon | T102: https://pimart-card-production.up.railway.app/products/%E5%AE%9D%E7%9F%B3%E5%8C%85%E7%AC%AC%E4%BA%8C%E5%BC%B9-box-%E7%AE%80%E4%B8%AD
...

Sheet 海贼王
A1: 海贼王 · PIMART
A2: 【大纲 1 / 2】点「1」只显示原盒主行（日常改库存/售价）。点「2」或行号旁「+」展开散包/原箱（有规格的新品写到这一层）。新品：先写规格=原盒，再在下方挂散包、原箱两行。
A4: 商品名 | B4: 系列 | C4: 盒型/类型 | D4: 规格 | E4: 销售状态 | F4: 库存 | G4: 销售价(JPY) | H4: 成本价(CNY) | I4: 语言 | J4: 网站状态 | K4: 是否预售 | L4: 首页推荐 | M4: 发售日 | N4: 发货天数 | O4: 图片 | P4: 优先级 | Q4: 商品类型 | R4: 备注 | S4: 商品ID | T4: SKU/Slug | U4: 游戏 | V4: 商品链接
A5: OPC 主弹补充包（新→旧）
A6: OPC-16 决战之时 原盒（简中） | B6: OPC-16 | C6: 原盒 | D6: 原盒 | E6: 售罄 | F6: 0 | G6: 5500 | I6: 简中 | J6: 未上架 | K6: 否 | M6: 2026-05-30T00:00:00 | O6: /products/onepiece-official/opc-16-pack.png | Q6: 扩充包 | R6: 官方 onepiece-cardgame.cn 已发售（主线编号弹，本店缺失（最新一弹）），本店未查到对应商品页，暂未上架。价格/库存/成本待你核实补录。 | 官方：决战之时。对照站内DB/集换社补库存价。 | U6: 海贼王
A7: OPC-16 决战之时 散包（简中） | B7: OPC-16 | C7: 原盒 | D7: 散包 | E7: 售罄 | F7: 0 | G7: 200 | I7: 简中 | J7: 未上架 | K7: 否 | M7: 2026-05-30T00:00:00 | O7: /products/onepiece-official/opc-16-pack.png | Q7: 扩充包 | R7: 官方 onepiece-cardgame.cn 已发售（主线编号弹，本店缺失（最新一弹）），本店未查到对应商品页，暂未上架。价格/库存/成本待你核实补录。 | 官方：决战之时。对照站内DB/集换社补库存价。 | U7: 海贼王
A8: OPC-16 决战之时 原箱（简中） | B8: OPC-16 | C8: 原盒 | D8: 原箱 | E8: 售罄 | F8: 0 | G8: 66000 | I8: 简中 | J8: 未上架 | K8: 否 | M8: 2026-05-30T00:00:00 | O8: /products/onepiece-official/opc-16-pack.png | Q8: 扩充包 | R8: 官方 onepiece-cardgame.cn 已发售（主线编号弹，本店缺失（最新一弹）），本店未查到对应商品页，暂未上架。价格/库存/成本待你核实补录。 | 官方：决战之时。对照站内DB/集换社补库存价。 | U8: 海贼王
A9: OPC-15 神之岛的冒险 原盒（简中） | B9: OPC-15 | C9: 原盒 | D9: 原盒 | E9: 售罄 | F9: 0 | G9: 5500 | I9: 简中 | J9: 上架 | K9: 否 | M9: 2026-03-14T00:00:00 | O9: /products/onepiece-official/opc-15-pack.png | Q9: 扩充包 | R9: 成本价/成本汇率待补录（Obsidian 暂无海贼王产品笔记）。 官方发售日 2026-03-14（来自 onepiece-cardgame.cn 官方数据）。 | 官方：神之岛的冒险。对照站内DB/集换社补库存价。 | T9: opc-15-adventure-gods-island-box | U9: One Piece | V9: https://pimart-card-production.up.railway.app/products/opc-15-adventure-gods-island-box
A10: OPC-15 神之岛的冒险 散包（简中） | B10: OPC-15 | C10: 原盒 | D10: 散包 | E10: 售罄 | F10: 0 | G10: 200 | I10: 简中 | J10: 上架 | K10: 否 | M10: 2026-03-14T00:00:00 | O10: /products/onepiece-official/opc-15-pack.png | Q10: 扩充包 | R10: 成本价/成本汇率待补录（Obsidian 暂无海贼王产品笔记）。 官方发售日 2026-03-14（来自 onepiece-cardgame.cn 官方数据）。 | 官方：神之岛的冒险。对照站内DB/集换社补库存价。 | T10: opc-15-adventure-gods-island-box | U10: One Piece | V10: https://pimart-card-production.up.railway.app/products/opc-15-adventure-gods-island-box
A11: OPC-15 神之岛的冒险 原箱（简中） | B11: OPC-15 | C11: 原盒 | D11: 原箱 | E11: 售罄 | F11: 0 | G11: 66000 | I11: 简中 | J11: 上架 | K11: 否 | M11: 2026-03-14T00:00:00 | O11: /products/onepiece-official/opc-15-pack.png | Q11: 扩充包 | R11: 成本价/成本汇率待补录（Obsidian 暂无海贼王产品笔记）。 官方发售日 2026-03-14（来自 onepiece-cardgame.cn 官方数据）。 | 官方：神之岛的冒险。对照站内DB/集换社补库存价。 | T11: opc-15-adventure-gods-island-box | U11: One Piece | V11: https://pimart-card-production.up.railway.app/products/opc-15-adventure-gods-island-box
A12: OPC-14 苍海七杰 原盒（简中） | B12: OPC-14 | C12: 原盒 | D12: 原盒 | E12: 售罄 | F12: 0 | G12: 5500 | I12: 简中 | J12: 上架 | K12: 否 | M12: 2025-12-04T00:00:00 | O12: /products/onepiece-official/opc-14-pack.png | Q12: 扩充包 | R12: 成本价/成本汇率待补录（Obsidian 暂无海贼王产品笔记）。 官方发售日 2025-12-04（来自 onepiece-cardgame.cn 官方数据）。 | 官方：苍海七杰。对照站内DB/集换社补库存价。 | T12: opc-14-cyan-sea-seven-box | U12: One Piece | V12: https://pimart-card-production.up.railway.app/products/opc-14-cyan-sea-seven-box
A13: OPC-14 苍海七杰 散包（简中） | B13: OPC-14 | C13: 原盒 | D13: 散包 | E13: 售罄 | F13: 0 | G13: 200 | I13: 简中 | J13: 上架 | K13: 否 | M13: 2025-12-04T00:00:00 | O13: /products/onepiece-official/opc-14-pack.png | Q13: 扩充包 | R13: 成本价/成本汇率待补录（Obsidian 暂无海贼王产品笔记）。 官方发售日 2025-12-04（来自 onepiece-cardgame.cn 官方数据）。 | 官方：苍海七杰。对照站内DB/集换社补库存价。 | T13: opc-14-cyan-sea-seven-box | U13: One Piece | V13: https://pimart-card-production.up.railway.app/products/opc-14-cyan-sea-seven-box
A14: OPC-14 苍海七杰 原箱（简中） | B14: OPC-14 | C14: 原盒 | D14: 原箱 | E14: 售罄 | F14: 0 | G14: 66000 | I14: 简中 | J14: 上架 | K14: 否 | M14: 2025-12-04T00:00:00 | O14: /products/onepiece-official/opc-14-pack.png | Q14: 扩充包 | R14: 成本价/成本汇率待补录（Obsidian 暂无海贼王产品笔记）。 官方发售日 2025-12-04（来自 onepiece-cardgame.cn 官方数据）。 | 官方：苍海七杰。对照站内DB/集换社补库存价。 | T14: opc-14-cyan-sea-seven-box | U14: One Piece | V14: https://pimart-card-production.up.railway.app/products/opc-14-cyan-sea-seven-box
A15: OPC-13 继承的意志 原盒（简中） | B15: OPC-13 | C15: 原盒 | D15: 原盒 | E15: 售罄 | F15: 0 | G15: 5500 | I15: 简中 | J15: 未上架 | K15: 否 | M15: 2025-09-16T00:00:00 | O15: /products/onepiece-official/opc-13-pack.png | Q15: 扩充包 | R15: 官方中文名：继承的意志。简中定价/库存待对照集换社与官网补录。 | U15: 海贼王
A16: OPC-13 继承的意志 散包（简中） | B16: OPC-13 | C16: 原盒 | D16: 散包 | E16: 售罄 | F16: 0 | G16: 200 | I16: 简中 | J16: 未上架 | K16: 否 | M16: 2025-09-16T00:00:00 | O16: /products/onepiece-official/opc-13-pack.png | Q16: 扩充包 | R16: 官方 onepiece-cardgame.cn 已发售（主线编号弹，本店缺失），本店未查到对应商品页，暂未上架。价格/库存/成本待你核实补录。 | 官方：继承的意志。对照站内DB/集换社补库存价。 | U16: 海贼王
A17: OPC-13 继承的意志 原箱（简中） | B17: OPC-13 | C17: 原盒 | D17: 原箱 | E17: 售罄 | F17: 0 | G17: 66000 | I17: 简中 | J17: 未上架 | K17: 否 | M17: 2025-09-16T00:00:00 | O17: /products/onepiece-official/opc-13-pack.png | Q17: 扩充包 | R17: 官方 onepiece-cardgame.cn 已发售（主线编号弹，本店缺失），本店未查到对应商品页，暂未上架。价格/库存/成本待你核实补录。 | 官方：继承的意志。对照站内DB/集换社补库存价。 | U17: 海贼王
A18: OPC-12 师徒之绊 原盒（简中） | B18: OPC-12 | C18: 原盒 | D18: 原盒 | E18: 售罄 | F18: 0 | G18: 5500 | I18: 简中 | J18: 未上架 | K18: 否 | M18: 2025-07-17T00:00:00 | O18: /products/onepiece-official/opc-12-pack.png | Q18: 扩充包 | R18: 官方中文名：师徒之绊。简中定价/库存待对照集换社与官网补录。 | U18: 海贼王
A19: OPC-12 师徒之绊 散包（简中） | B19: OPC-12 | C19: 原盒 | D19: 散包 | E19: 售罄 | F19: 0 | G19: 200 | I19: 简中 | J19: 未上架 | K19: 否 | M19: 2025-07-17T00:00:00 | O19: /products/onepiece-official/opc-12-pack.png | Q19: 扩充包 | R19: 官方 onepiece-cardgame.cn 已发售（主线编号弹，本店缺失），本店未查到对应商品页，暂未上架。价格/库存/成本待你核实补录。 | 官方：师徒之绊。对照站内DB/集换社补库存价。 | U19: 海贼王
A20: OPC-12 师徒之绊 原箱（简中） | B20: OPC-12 | C20: 原盒 | D20: 原箱 | E20: 售罄 | F20: 0 | G20: 66000 | I20: 简中 | J20: 未上架 | K20: 否 | M20: 2025-07-17T00:00:00 | O20: /products/onepiece-official/opc-12-pack.png | Q20: 扩充包 | R20: 官方 onepiece-cardgame.cn 已发售（主线编号弹，本店缺失），本店未查到对应商品页，暂未上架。价格/库存/成本待你核实补录。 | 官方：师徒之绊。对照站内DB/集换社补库存价。 | U20: 海贼王
A21: OPC-11 神速之拳 原盒（简中） | B21: OPC-11 | C21: 原盒 | D21: 原盒 | E21: 在售 | F21: 100 | G21: 5500 | I21: 简中 | J21: 上架 | K21: 否 | M21: 2025-04-09T00:00:00 | O21: /products/onepiece-official/opc-11-pack.png | Q21: 扩充包 | R21: 成本价/成本汇率待补录（Obsidian 暂无海贼王产品笔记）。网站显示「有货」但未展示精确库存数字，请手动核实后填入。 官方发售日 2025-04-09（来自 onepiece-cardgame.cn 官方数据）。 | 官方：神速之拳。对照站内DB/集换社补库存价。 | T21: opc-11-divine-speed-box | U21: One Piece | V21: https://pimart-card-production.up.railway.app/products/opc-11-divine-speed-box
A22: OPC-11 神速之拳 散包（简中） | B22: OPC-11 | C22: 原盒 | D22: 散包 | E22: 在售 | F22: 400 | G22: 200 | I22: 简中 | J22: 上架 | K22: 否 | M22: 2025-04-09T00:00:00 | O22: /products/onepiece-official/opc-11-pack.png | Q22: 扩充包 | R22: 成本价/成本汇率待补录（Obsidian 暂无海贼王产品笔记）。网站显示「有货」但未展示精确库存数字，请手动核实后填入。 官方发售日 2025-04-09（来自 onepiece-cardgame.cn 官方数据）。 | 官方：神速之拳。对照站内DB/集换社补库存价。 | T22: opc-11-divine-speed-box | U22: One Piece | V22: https://pimart-card-production.up.railway.app/products/opc-11-divine-speed-box
A23: OPC-11 神速之拳 原箱（简中） | B23: OPC-11 | C23: 原盒 | D23: 原箱 | E23: 在售 | F23: 8 | G23: 66000 | I23: 简中 | J23: 上架 | K23: 否 | M23: 2025-04-09T00:00:00 | O23: /products/onepiece-official/opc-11-pack.png | Q23: 扩充包 | R23: 成本价/成本汇率待补录（Obsidian 暂无海贼王产品笔记）。网站显示「有货」但未展示精确库存数字，请手动核实后填入。 官方发售日 2025-04-09（来自 onepiece-cardgame.cn 官方数据）。 | 官方：神速之拳。对照站内DB/集换社补库存价。 | T23: opc-11-divine-speed-box | U23: One Piece | V23: https://pimart-card-production.up.railway.app/products/opc-11-divine-speed-box
A24: OPC-10 王之血脉 原盒（简中） | B24: OPC-10 | C24: 原盒 | D24: 原盒 | E24: 在售 | F24: 100 | G24: 5500 | I24: 简中 | J24: 上架 | K24: 否 | M24: 2025-01-16T00:00:00 | O24: /products/onepiece-official/opc-10-pack.png | Q24: 扩充包 | R24: 成本价/成本汇率待补录（Obsidian 暂无海贼王产品笔记）。网站显示「有货」但未展示精确库存数字，请手动核实后填入。 官方发售日 2025-01-16（来自 onepiece-cardgame.cn 官方数据）。 | 官方：王之血脉。对照站内DB/集换社补库存价。 | T24: opc-10-royal-blood-box | U24: One Piece | V24: https://pimart-card-production.up.railway.app/products/opc-10-royal-blood-box
A25: OPC-10 王之血脉 散包（简中） | B25: OPC-10 | C25: 原盒 | D25: 散包 | E25: 在售 | F25: 400 | G25: 200 | I25: 简中 | J25: 上架 | K25: 否 | M25: 2025-01-16T00:00:00 | O25: /products/onepiece-official/opc-10-pack.png | Q25: 扩充包 | R25: 成本价/成本汇率待补录（Obsidian 暂无海贼王产品笔记）。网站显示「有货」但未展示精确库存数字，请手动核实后填入。 官方发售日 2025-01-16（来自 onepiece-cardgame.cn 官方数据）。 | 官方：王之血脉。对照站内DB/集换社补库存价。 | T25: opc-10-royal-blood-box | U25: One Piece | V25: https://pimart-card-production.up.railway.app/products/opc-10-royal-blood-box
A26: OPC-10 王之血脉 原箱（简中） | B26: OPC-10 | C26: 原盒 | D26: 原箱 | E26: 在售 | F26: 8 | G26: 66000 | I26: 简中 | J26: 上架 | K26: 否 | M26: 2025-01-16T00:00:00 | O26: /products/onepiece-official/opc-10-pack.png | Q26: 扩充包 | R26: 成本价/成本汇率待补录（Obsidian 暂无海贼王产品笔记）。网站显示「有货」但未展示精确库存数字，请手动核实后填入。 官方发售日 2025-01-16（来自 onepiece-cardgame.cn 官方数据）。 | 官方：王之血脉。对照站内DB/集换社补库存价。 | T26: opc-10-royal-blood-box | U26: One Piece | V26: https://pimart-card-production.up.railway.app/products/opc-10-royal-blood-box
A27: OPC-09 新帝降临 原盒（简中） | B27: OPC-09 | C27: 原盒 | D27: 原盒 | E27: 在售 | F27: 100 | G27: 5500 | I27: 简中 | J27: 上架 | K27: 否 | M27: 2024-10-18T00:00:00 | O27: /products/onepiece-official/opc-09-pack.png | Q27: 扩充包 | R27: 成本价/成本汇率待补录（Obsidian 暂无海贼王产品笔记）。网站显示「有货」但未展示精确库存数字，请手动核实后填入。 官方发售日 2024-10-18（来自 onepiece-cardgame.cn 官方数据）。 | 官方：新帝降临。对照站内DB/集换社补库存价。 | T27: opc-09-emperors-new-world-box | U27: One Piece | V27: https://pimart-card-production.up.railway.app/products/opc-09-emperors-new-world-box
A28: OPC-09 新帝降临 散包（简中） | B28: OPC-09 | C28: 原盒 | D28: 散包 | E28: 在售 | F28: 400 | G28: 200 | I28: 简中 | J28: 上架 | K28: 否 | M28: 2024-10-18T00:00:00 | O28: /products/onepiece-official/opc-09-pack.png | Q28: 扩充包 | R28: 成本价/成本汇率待补录（Obsidian 暂无海贼王产品笔记）。网站显示「有货」但未展示精确库存数字，请手动核实后填入。 官方发售日 2024-10-18（来自 onepiece-cardgame.cn 官方数据）。 | 官方：新帝降临。对照站内DB/集换社补库存价。 | T28: opc-09-emperors-new-world-box | U28: One Piece | V28: https://pimart-card-production.up.railway.app/products/opc-09-emperors-new-world-box
A29: OPC-09 新帝降临 原箱（简中） | B29: OPC-09 | C29: 原盒 | D29: 原箱 | E29: 在售 | F29: 8 | G29: 66000 | I29: 简中 | J29: 上架 | K29: 否 | M29: 2024-10-18T00:00:00 | O29: /products/onepiece-official/opc-09-pack.png | Q29: 扩充包 | R29: 成本价/成本汇率待补录（Obsidian 暂无海贼王产品笔记）。网站显示「有货」但未展示精确库存数字，请手动核实后填入。 官方发售日 2024-10-18（来自 onepiece-cardgame.cn 官方数据）。 | 官方：新帝降临。对照站内DB/集换社补库存价。 | T29: opc-09-emperors-new-world-box | U29: One Piece | V29: https://pimart-card-production.up.railway.app/products/opc-09-emperors-new-world-box
A30: OPC-08 双子传说 原盒（简中） | B30: OPC-08 | C30: 原盒 | D30: 原盒 | E30: 在售 | F30: 100 | G30: 5800 | I30: 简中 | J30: 上架 | K30: 否 | M30: 2024-07-15T00:00:00 | O30: /products/onepiece-official/opc-08-pack.png | Q30: 扩充包 | R30: 成本价/成本汇率待补录（Obsidian 暂无海贼王产品笔记）。网站显示「有货」但未展示精确库存数字，请手动核实后填入。 官方发售日 2024-07-15；官方接口名称为「传说的强者」，与本店商品名不完全一致，请核实是否为同一弹。 | 官方：双子传说。对照站内DB/集换社补库存价。 | T30: opc-08-two-legends-box | U30: One Piece | V30: https://pimart-card-production.up.railway.app/products/opc-08-two-legends-box
A31: OPC-08 双子传说 散包（简中） | B31: OPC-08 | C31: 原盒 | D31: 散包 | E31: 在售 | F31: 400 | G31: 200 | I31: 简中 | J31: 上架 | K31: 否 | M31: 2024-07-15T00:00:00 | O31: /products/onepiece-official/opc-08-pack.png | Q31: 扩充包 | R31: 成本价/成本汇率待补录（Obsidian 暂无海贼王产品笔记）。网站显示「有货」但未展示精确库存数字，请手动核实后填入。 官方发售日 2024-07-15；官方接口名称为「传说的强者」，与本店商品名不完全一致，请核实是否为同一弹。 | 官方：双子传说。对照站内DB/集换社补库存价。 | T31: opc-08-two-legends-box | U31: One Piece | V31: https://pimart-card-production.up.railway.app/products/opc-08-two-legends-box
A32: OPC-08 双子传说 原箱（简中） | B32: OPC-08 | C32: 原盒 | D32: 原箱 | E32: 在售 | F32: 100 | G32: 69600 | I32: 简中 | J32: 上架 | K32: 否 | M32: 2024-07-15T00:00:00 | O32: /products/onepiece-official/opc-08-pack.png | Q32: 扩充包 | R32: 成本价/成本汇率待补录（Obsidian 暂无海贼王产品笔记）。网站显示「有货」但未展示精确库存数字，请手动核实后填入。 官方发售日 2024-07-15；官方接口名称为「传说的强者」，与本店商品名不完全一致，请核实是否为同一弹。 | 官方：双子传说。对照站内DB/集换社补库存价。 | T32: opc-08-two-legends-box | U32: One Piece | V32: https://pimart-card-production.up.railway.app/products/opc-08-two-legends-box
... A53: OPC-01 冒险的黎明 原箱（简中） | B53: OPC-01 | C53: 原盒 | D53: 原箱 | E53: 售罄 | F53: 0 | G53: 117600 | I53: 简中 | J53: 上架 | K53: 否 | M53: 2022-11-18T00:00:00 | O53: /products/onepiece-official/opc-01-pack.png | Q53: 扩充包 | R53: 成本价/成本汇率待补录（Obsidian 暂无海贼王产品笔记）。 官方发售日 2022-11-18（来自 onepiece-cardgame.cn 官方数据）。 | 官方：冒险的黎明。对照站内DB/集换社补库存价。 | T53: opc-01-romance-dawn-box | U53: One Piece | V53: https://pimart-card-production.up.railway.app/products/opc-01-romance-dawn-box
A55: EB 特别补充包 | O55: /products/placeholder.svg
A56: EBC-04 艾格赫德危机 原盒（简中） | B56: EBC-04 | C56: 原盒 | D56: 原盒 | E56: 售罄 | F56: 0 | I56: 简中 | J56: 未上架 | K56: 否 | M56: 2026-02-02T00:00:00 | O56: /products/onepiece-official/ebc-04-pack.png | Q56: 扩充包 | R56: 特别补充包 艾格赫德危机。简中定价待官方/集换社。 | U56: 海贼王
A57: EBC-04 艾格赫德危机 散包（简中） | B57: EBC-04 | C57: 原盒 | D57: 散包 | E57: 在售 | F57: 0 | I57: 简中 | J57: 未上架 | K57: 否 | M57: 2026-02-02T00:00:00 | O57: /products/onepiece-official/ebc-04-pack.png | Q57: 扩充包 | R57: 官方 onepiece-cardgame.cn 已发售（特别篇），本店未查到对应商品页，暂未上架。价格/库存/成本待你核实补录。 | U57: 海贼王
A58: EBC-04 艾格赫德危机 原箱（简中） | B58: EBC-04 | C58: 原盒 | D58: 原箱 | E58: 在售 | F58: 0 | I58: 简中 | J58: 未上架 | K58: 否 | M58: 2026-02-02T00:00:00 | O58: /products/onepiece-official/ebc-04-pack.png | Q58: 扩充包 | R58: 官方 onepiece-cardgame.cn 已发售（特别篇），本店未查到对应商品页，暂未上架。价格/库存/成本待你核实补录。 | U58: 海贼王
A59: EBC-03 ONE PIECE Heroines Edition 原盒（简中） | B59: EBC-03 | C59: 原盒 | D59: 原盒 | E59: 售罄 | F59: 0 | G59: 7500 | I59: 简中 | J59: 上架 | K59: 否 | M59: 2025-11-07T00:00:00 | Q59: 扩充包 | R59: 官方 onepiece-cardgame.cn 已发售（女角色主题特别篇），本店未查到对应商品页，暂未上架。价格/库存/成本待你核实补录。 | U59: 海贼王
A60: EBC-03 ONE PIECE Heroines Edition 散包（简中） | B60: EBC-03 | C60: 原盒 | D60: 散包 | E60: 在售 | F60: 0 | G60: 312 | I60: 简中 | J60: 未上架 | K60: 否 | M60: 2025-11-07T00:00:00 | Q60: 扩充包 | R60: 官方 onepiece-cardgame.cn 已发售（女角色主题特别篇），本店未查到对应商品页，暂未上架。价格/库存/成本待你核实补录。 | U60: 海贼王
A61: EBC-03 ONE PIECE Heroines Edition 原箱（简中） | B61: EBC-03 | C61: 原盒 | D61: 原箱 | E61: 在售 | F61: 0 | G61: 90000 | I61: 简中 | J61: 未上架 | K61: 否 | M61: 2025-11-07T00:00:00 | Q61: 扩充包 | R61: 官方 onepiece-cardgame.cn 已发售（女角色主题特别篇），本店未查到对应商品页，暂未上架。价格/库存/成本待你核实补录。 | U61: 海贼王
A62: EBC-02 Anime 25th Collection 原盒（简中） | B62: EBC-02 | C62: 原盒 | D62: 原盒 | E62: 售罄 | F62: 0 | G62: 7800 | I62: 简中 | J62: 上架 | K62: 否 | M62: 2025-03-12T00:00:00 | Q62: 扩充包 | R62: 官方 onepiece-cardgame.cn 已发售（动画25周年特别篇），本店未查到对应商品页，暂未上架。价格/库存/成本待你核实补录。 | U62: 海贼王
A63: EBC-02 Anime 25th Collection 散包（简中） | B63: EBC-02 | C63: 原盒 | D63: 散包 | E63: 在售 | F63: 0 | G63: 325 | I63: 简中 | J63: 未上架 | K63: 否 | M63: 2025-03-12T00:00:00 | Q63: 扩充包 | R63: 官方 onepiece-cardgame.cn 已发售（动画25周年特别篇），本店未查到对应商品页，暂未上架。价格/库存/成本待你核实补录。 | U63: 海贼王
A64: EBC-02 Anime 25th Collection 原箱（简中） | B64: EBC-02 | C64: 原盒 | D64: 原箱 | E64: 在售 | F64: 0 | G64: 93600 | I64: 简中 | J64: 未上架 | K64: 否 | M64: 2025-03-12T00:00:00 | Q64: 扩充包 | R64: 官方 onepiece-cardgame.cn 已发售（动画25周年特别篇），本店未查到对应商品页，暂未上架。价格/库存/成本待你核实补录。 | U64: 海贼王
A65: EB-01 特别补充包 纪念收藏合集 原盒（简中） | B65: EB-01 | C65: 原盒 | D65: 原盒 | E65: 未上架 | F65: 0 | I65: 简中 | J65: 未上架 | K65: 否 | M65: 2024-03-20T00:00:00 | O65: /products/onepiece-official/ebc-01-pack.png | Q65: 特殊卡包 | R65: 官方 onepiece-cardgame.cn 已发售（特别篇，无编号），本店未查到对应商品页，暂未上架。价格/库存/成本待你核实补录。 | T65: eb-01-memorial-collection-box | U65: 海贼王
A66: PRB 豪华补充包 / 典藏包 | O66: /products/placeholder.svg
A67: PRBC-02 历代典藏合集 Vol.2 原盒（简中） | B67: PRBC-02 | C67: 原盒 | D67: 原盒 | E67: 售罄 | F67: 0 | I67: 简中 | J67: 未上架 | K67: 否 | M67: 2025-08-19T00:00:00 | O67: /products/onepiece-official/prbc-02-pack.png | Q67: 扩充包 | R67: 豪华补充包 历代典藏合集 Vol.2。简中定价待官方/集换社。 | U67: 海贼王
A68: PRBC-02 历代典藏合集 Vol.2 散包（简中） | B68: PRBC-02 | C68: 原盒 | D68: 散包 | E68: 在售 | F68: 0 | I68: 简中 | J68: 未上架 | K68: 否 | M68: 2025-08-19T00:00:00 | O68: /products/onepiece-official/prbc-02-pack.png | Q68: 扩充包 | R68: 官方 onepiece-cardgame.cn 已发售（豪华合集），本店未查到对应商品页，暂未上架。价格/库存/成本待你核实补录。 | U68: 海贼王
A69: PRBC-02 历代典藏合集 Vol.2 原箱（简中） | B69: PRBC-02 | C69: 原盒 | D69: 原箱 | E69: 在售 | F69: 0 | I69: 简中 | J69: 未上架 | K69: 否 | M69: 2025-08-19T00:00:00 | O69: /products/onepiece-official/prbc-02-pack.png | Q69: 扩充包 | R69: 官方 onepiece-cardgame.cn 已发售（豪华合集），本店未查到对应商品页，暂未上架。价格/库存/成本待你核实补录。 | U69: 海贼王
A70: PRBC-01 历代典藏合集 原盒（简中） | B70: PRBC-01 | C70: 原盒 | D70: 原盒 | E70: 售罄 | F70: 0 | I70: 简中 | J70: 未上架 | K70: 否 | M70: 2024-09-17T00:00:00 | O70: /products/onepiece-official/prbc-01-pack.png | Q70: 扩充包 | R70: 豪华补充包 历代典藏合集。简中定价待官方/集换社。 | U70: 海贼王
A71: PRBC-01 历代典藏合集 散包（简中） | B71: PRBC-01 | C71: 原盒 | D71: 散包 | E71: 在售 | F71: 0 | I71: 简中 | J71: 未上架 | K71: 否 | M71: 2024-09-17T00:00:00 | O71: /products/onepiece-official/prbc-01-pack.png | Q71: 扩充包 | R71: 官方 onepiece-cardgame.cn 已发售（豪华合集），本店未查到对应商品页，暂未上架。价格/库存/成本待你核实补录。 | U71: 海贼王
A72: PRBC-01 历代典藏合集 原箱（简中） | B72: PRBC-01 | C72: 原盒 | D72: 原箱 | E72: 在售 | F72: 0 | I72: 简中 | J72: 未上架 | K72: 否 | M72: 2024-09-17T00:00:00 | O72: /products/onepiece-official/prbc-01-pack.png | Q72: 扩充包 | R72: 官方 onepiece-cardgame.cn 已发售（豪华合集），本店未查到对应商品页，暂未上架。价格/库存/成本待你核实补录。 | U72: 海贼王
A74: 挂盒 / 预组 / STC
A75: 基本卡组 对战进阶套组2026（官方名称，简中定价待官方公布） | B75: STC-31~36 | C75: 卡组 | D75: 原盒 | E75: 未上架 | F75: 0 | I75: 简中 | J75: 未上架 | K75: 否 | M75: 2026-07-11T00:00:00 | O75: /products/onepiece-official/stc-31-36-decks.png | Q75: 挂盒 | R75: 官方 onepiece-cardgame.cn 已发售的构筑卡组，本店未查到对应商品页，暂未上架。价格/库存/成本待你核实补录。 | U75: One Piece
A76: 基本卡组 艾格赫德（官方名称，简中定价待官方公布） | B76: STC-29 | C76: 卡组 | D76: 原盒 | E76: 未上架 | F76: 0 | I76: 简中 | J76: 未上架 | K76: 否 | M76: 2025-12-26T00:00:00 | O76: /products/onepiece-official/stc-29-deck.png | Q76: 挂盒 | R76: 官方 onepiece-cardgame.cn 已发售的构筑卡组，本店未查到对应商品页，暂未上架。价格/库存/成本待你核实补录。 | U76: One Piece
A77: 基本卡组 对战进阶套组2025（官方名称，简中定价待官方公布） | B77: STC-23~28 | C77: 卡组 | D77: 原盒 | E77: 未上架 | F77: 0 | I77: 简中 | J77: 未上架 | K77: 否 | M77: 2025-08-07T00:00:00 | O77: /products/onepiece-official/stc-23-28-decks.png | Q77: 挂盒 | R77: 官方 onepiece-cardgame.cn 已发售的构筑卡组，本店未查到对应商品页，暂未上架。价格/库存/成本待你核实补录。 | U77: One Piece
A78: 基本卡组 两年后再出发（官方名称，简中定价待官方公布） | B78: STC-14 | C78: 卡组 | D78: 原盒 | E78: 未上架 | F78: 0 | I78: 简中 | J78: 未上架 | K78: 否 | M78: 2024-06-25T00:00:00 | O78: /products/onepiece-official/stc-14-deck.png | Q78: 挂盒 | R78: 官方 onepiece-cardgame.cn 已发售的构筑卡组，本店未查到对应商品页，暂未上架。价格/库存/成本待你核实补录。 | U78: One Piece
A79: 究极进阶卡组 奇迹的再会（官方名称，简中定价待官方公布） | B79: STC-13 | C79: 卡组 | D79: 原盒 | E79: 未上架 | F79: 0 | I79: 简中 | J79: 未上架 | K79: 否 | M79: 2024-03-13T00:00:00 | O79: /products/onepiece-official/stc-13-deck.png | Q79: 挂盒 | R79: 官方 onepiece-cardgame.cn 已发售的构筑卡组，本店未查到对应商品页，暂未上架。价格/库存/成本待你核实补录。 | U79: One Piece
A80: 基本卡组 佐罗＆山智（官方名称，简中定价待官方公布） | B80: STC-12 | C80: 卡组 | D80: 原盒 | E80: 未上架 | F80: 0 | I80: 简中 | J80: 未上架 | K80: 否 | M80: 2024-01-12T00:00:00 | O80: /products/onepiece-official/stc-12-deck.png | Q80: 挂盒 | R80: 官方 onepiece-cardgame.cn 已发售的构筑卡组，本店未查到对应商品页，暂未上架。价格/库存/成本待你核实补录。 | U80: One Piece
A81: 究极进阶卡组 三方船长集结（官方名称，简中定价待官方公布） | B81: STC-10 | C81: 卡组 | D81: 原盒 | E81: 未上架 | F81: 0 | I81: 简中 | J81: 未上架 | K81: 否 | M81: 2023-10-27T00:00:00 | O81: /products/onepiece-official/stc-10-deck.png | Q81: 挂盒 | R81: 官方 onepiece-cardgame.cn 已发售的构筑卡组，本店未查到对应商品页，暂未上架。价格/库存/成本待你核实补录。 | U81: One Piece
A82: 基本卡组 继承御殿遗志的人（官方名称，简中定价待官方公布） | B82: STC-09 | C82: 卡组 | D82: 原盒 | E82: 未上架 | F82: 0 | I82: 简中 | J82: 未上架 | K82: 否 | M82: 2023-08-11T00:00:00 | O82: /products/onepiece-official/stc-09-deck.png | Q82: 挂盒 | R82: 官方 onepiece-cardgame.cn 已发售的构筑卡组，本店未查到对应商品页，暂未上架。价格/库存/成本待你核实补录。 | U82: One Piece
A83: 基本卡组 第五个海上皇帝（官方名称，简中定价待官方公布） | B83: STC-08 | C83: 卡组 | D83: 原盒 | E83: 未上架 | F83: 0 | I83: 简中 | J83: 未上架 | K83: 否 | M83: 2023-08-11T00:00:00 | O83: /products/onepiece-official/stc-08-deck.png | Q83: 挂盒 | R83: 官方 onepiece-cardgame.cn 已发售的构筑卡组，本店未查到对应商品页，暂未上架。价格/库存/成本待你核实补录。 | U83: One Piece
A84: 基本卡组 大妈海盗团（官方名称，简中定价待官方公布） | B84: STC-07 | C84: 卡组 | D84: 原盒 | E84: 未上架 | F84: 0 | I84: 简中 | J84: 未上架 | K84: 否 | M84: 2023-04-21T00:00:00 | O84: /products/onepiece-official/stc-07-deck.png | Q84: 挂盒 | R84: 官方 onepiece-cardgame.cn 已发售的构筑卡组，本店未查到对应商品页，暂未上架。价格/库存/成本待你核实补录。 | U84: One Piece
A85: STC-06 基本卡组 绝对正义（简中） | B85: STC-06 | C85: 卡组 | D85: 原盒 | E85: 在售 | F85: 100 | G85: 1380 | I85: 简中 | J85: 未上架 | K85: 否 | M85: 2023-01-06T00:00:00 | O85: /products/onepiece-official/stc-06-deck.jpg | Q85: 挂盒 | R85: 官方 onepiece-cardgame.cn 已发售的构筑卡组，本店未查到对应商品页，暂未上架。价格/库存/成本待你核实补录。 | U85: 海贼王
A86: 基本卡组 ONE PIECE FILM edition（官方名称，简中定价待官方公布） | B86: STC-05 | C86: 卡组 | D86: 原盒 | E86: 未上架 | F86: 0 | I86: 简中 | J86: 未上架 | K86: 否 | M86: 2022-12-09T00:00:00 | O86: /products/onepiece-official/stc-05-deck.png | Q86: 挂盒 | R86: 官方 onepiece-cardgame.cn 已发售的构筑卡组，本店未查到对应商品页，暂未上架。价格/库存/成本待你核实补录。 | U86: One Piece
A87: STC-01 基本卡组 草帽一伙（简中） | B87: STC-01 | C87: 预组 | D87: 原盒 | E87: 在售 | F87: 100 | G87: 1380 | I87: 简中 | J87: 上架 | K87: 否 | L87: 否 | N87: 6 | O87: /products/onepiece-official/stc-01-deck.jpg | Q87: 预组 | R87: 来自网站 DB。 | T87: STC-01-草帽一伙-简中 | U87: 海贼王
A88: STC-02 基本卡组 超新星们（简中） | B88: STC-02 | C88: 预组 | D88: 原盒 | E88: 在售 | F88: 100 | G88: 1380 | I88: 简中 | J88: 上架 | K88: 否 | L88: 否 | N88: 6 | O88: /products/onepiece-official/stc-02-deck.jpg | Q88: 预组 | R88: 来自网站 DB。 | T88: STC-02-超新星们-简中 | U88: 海贼王
A89: STC-03 基本卡组 王下七武海（简中） | B89: STC-03 | C89: 预组 | D89: 原盒 | E89: 在售 | F89: 100 | G89: 1380 | I89: 简中 | J89: 上架 | K89: 否 | L89: 否 | N89: 6 | O89: /products/onepiece-official/stc-03-deck.jpg | Q89: 预组 | R89: 来自网站 DB。 | T89: STC-03-王下七武海-简中 | U89: 海贼王
A90: STC-04 基本卡组 百兽海盗团（简中） | B90: STC-04 | C90: 预组 | D90: 原盒 | E90: 在售 | F90: 100 | G90: 1380 | I90: 简中 | J90: 上架 | K90: 否 | L90: 否 | N90: 6 | O90: /products/onepiece-official/stc-04-deck.jpg | Q90: 预组 | R90: 来自网站 DB。 | T90: STC-04-百兽海盗团-简中 | U90: 海贼王
A91: 基本卡组 变档5档（官方名称，简中定价待官方公布） | B91: STC-? | C91: 卡组 | D91: 原盒 | E91: 未上架 | F91: 0 | I91: 简中 | J91: 未上架 | K91: 否 | M91: 2025-01-22T00:00:00 | O91: /products/onepiece-official/stc-15-deck.png | Q91: 挂盒 | R91: 官方 onepiece-cardgame.cn 已发售的构筑卡组，本店未查到对应商品页，暂未上架。价格/库存/成本待你核实补录。 | U91: One Piece
A92: 基本卡组 艾斯和纽哥特（官方名称，简中定价待官方公布） | B92: STC-? | C92: 预组 | D92: 原盒 | E92: 售罄 | F92: 0 | I92: 简中 | M92: 2025-06-05T00:00:00 | O92: /products/onepiece-official/stc-30-deck.png | Q92: 挂盒 | R92: 官方 onepiece-cardgame.cn 已发售的构筑卡组，本店未查到对应商品页，暂未上架。价格/库存/成本待你核实补录。 | U92: One Piece
A93: 基本卡组 路飞＆艾斯（官方名称，简中定价待官方公布） | B93: STC-? | C93: 卡组 | D93: 原盒 | E93: 未上架 | F93: 0 | I93: 简中 | J93: 未上架 | K93: 否 | M93: 2026-04-11T00:00:00 | O93: /products/onepiece-official/stc-22-deck.png | Q93: 挂盒 | R93: 官方 onepiece-cardgame.cn 已发售的构筑卡组，本店未查到对应商品页，暂未上架。价格/库存/成本待你核实补录。 | U93: One Piece
A95: 礼盒 / 周边
A96: 航海王卡牌对战 四周年纪念套装（简中） | B96: 航海王礼盒 | C96: 礼盒 | D96: 原盒 | E96: 未上架 | F96: 0 | G96: 0 | I96: 简中 | J96: 上架 | K96: 否 | L96: 否 | M96: 2026-12-01 00:00:00 | N96: 6 | O96: /products/onepiece-official/gift-128.png | Q96: 礼盒 | R96: 航海王卡牌对战简体中文版官方套装。官方商品 ID：128，价格待核。 | T96: onepiece-gift-128
A97: 豪华卡牌收藏 精选套装 Vol.6（简中） | B97: 航海王礼盒 | C97: 礼盒 | D97: 原盒 | E97: 未上架 | F97: 0 | G97: 0 | I97: 简中 | J97: 上架 | K97: 否 | L97: 否 | M97: 2026-03-27 08:00:00 | N97: 6 | O97: /products/onepiece-official/gift-123.png | Q97: 礼盒 | R97: 航海王卡牌对战简体中文版官方套装。官方商品 ID：123，价格待核。 | T97: onepiece-gift-123
A98: 航海王卡牌对战 豪华卡牌收藏 六种卡牌套装Vol.1（简中） | B98: 航海王礼盒 | C98: 礼盒 | D98: 原盒 | E98: 未上架 | F98: 0 | G98: 0 | I98: 简中 | J98: 上架 | K98: 否 | L98: 否 | M98: 2025-12-17 08:00:00 | N98: 6 | O98: /products/onepiece-official/gift-113.png | Q98: 礼盒 | R98: 航海王卡牌对战简体中文版官方套装。官方商品 ID：113，价格待核。 | T98: onepiece-gift-113
A99: 航海王卡牌对战 ONE PIECE Heroines Special Set（简中） | B99: 航海王礼盒 | C99: 礼盒 | D99: 原盒 | E99: 未上架 | F99: 0 | G99: 0 | I99: 简中 | J99: 上架 | K99: 否 | L99: 否 | M99: 2025-11-06 00:00:00 | N99: 6 | O99: /products/onepiece-official/gift-106.png | Q99: 礼盒 | R99: 航海王卡牌对战简体中文版官方套装。官方商品 ID：106，价格待核。 | T99: onepiece-gift-106
A100: 豪华卡牌收藏 精选套装 Vol.5（简中） | B100: 航海王礼盒 | C100: 礼盒 | D100: 原盒 | E100: 未上架 | F100: 0 | G100: 0 | I100: 简中 | J100: 上架 | K100: 否 | L100: 否 | M100: 2025-10-05 00:00:00 | N100: 6 | O100: /products/onepiece-official/gift-103.png | Q100: 礼盒 | R100: 航海王卡牌对战简体中文版官方套装。官方商品 ID：103，价格待核。 | T100: onepiece-gift-103
A101: 航海王卡牌对战 三周年纪念套装（简中） | B101: 航海王礼盒 | C101: 礼盒 | D101: 原盒 | E101: 未上架 | F101: 0 | G101: 0 | I101: 简中 | J101: 上架 | K101: 否 | L101: 否 | M101: 2025-12-26 16:00:00 | N101: 6 | O101: /products/onepiece-official/gift-94.png | Q101: 礼盒 | R101: 航海王卡牌对战简体中文版官方套装。官方商品 ID：94，价格待核。 | T101: onepiece-gift-94
A102: 豪华卡牌收藏 精选套装 Vol.4（简中） | B102: 航海王礼盒 | C102: 礼盒 | D102: 原盒 | E102: 未上架 | F102: 0 | G102: 0 | I102: 简中 | J102: 上架 | K102: 否 | L102: 否 | M102: 2025-05-20 16:00:00 | N102: 6 | O102: /products/onepiece-official/gift-90.png | Q102: 礼盒 | R102: 航海王卡牌对战简体中文版官方套装。官方商品 ID：90，价格待核。 | T102: onepiece-gift-90
A103: 航海王卡牌对战 迷你收藏套装（简中） | B103: 航海王礼盒 | C103: 礼盒 | D103: 原盒 | E103: 未上架 | F103: 0 | G103: 0 | I103: 简中 | J103: 上架 | K103: 否 | L103: 否 | M103: 2025-03-27 08:00:00 | N103: 6 | O103: /products/onepiece-official/gift-85.png | Q103: 礼盒 | R103: 航海王卡牌对战简体中文版官方套装。官方商品 ID：85，价格待核。 | T103: onepiece-gift-85
A104: 豪华卡牌收藏 日版两周年特别纪念（简体中文版）（简中） | B104: 航海王礼盒 | C104: 礼盒 | D104: 原盒 | E104: 未上架 | F104: 0 | G104: 0 | I104: 简中 | J104: 上架 | K104: 否 | L104: 否 | M104: 2025-03-23 00:00:00 | N104: 6 | O104: /products/onepiece-official/gift-84.png | Q104: 礼盒 | R104: 航海王卡牌对战简体中文版官方套装。官方商品 ID：84，价格待核。 | T104: onepiece-gift-84
A105: 豪华卡牌收藏 精选套装 Vol.3（简中） | B105: 航海王礼盒 | C105: 礼盒 | D105: 原盒 | E105: 未上架 | F105: 0 | G105: 0 | I105: 简中 | J105: 上架 | K105: 否 | L105: 否 | M105: 2024-11-01 16:00:02 | N105: 6 | O105: /products/onepiece-official/gift-67.png | Q105: 礼盒 | R105: 航海王卡牌对战简体中文版官方套装。官方商品 ID：67，价格待核。 | T105: onepiece-gift-67
A106: 豪华卡牌收藏 精选套装 Vol.2（简中） | B106: 航海王礼盒 | C106: 礼盒 | D106: 原盒 | E106: 未上架 | F106: 0 | G106: 0 | I106: 简中 | J106: 上架 | K106: 否 | L106: 否 | M106: 2024-07-25 08:00:01 | N106: 6 | O106: /products/onepiece-official/gift-62.png | Q106: 礼盒 | R106: 航海王卡牌对战简体中文版官方套装。官方商品 ID：62，价格待核。 | T106: onepiece-gift-62
A107: 豪华卡牌收藏 精选套装 Vol.1（简中） | B107: 航海王礼盒 | C107: 礼盒 | D107: 原盒 | E107: 未上架 | F107: 0 | G107: 0 | I107: 简中 | J107: 上架 | K107: 否 | L107: 否 | M107: 2024-03-02 16:00:00 | N107: 6 | O107: /products/onepiece-official/gift-49.png | Q107: 礼盒 | R107: 航海王卡牌对战简体中文版官方套装。官方商品 ID：49，价格待核。 | T107: onepiece-gift-49
... A110: 航海王卡牌对战 对战桌垫+卡牌盒套装 -25周年版- （简中） | B110: 航海王礼盒 | C110: 礼盒 | D110: 原盒 | E110: 未上架 | F110: 0 | G110: 0 | I110: 简中 | J110: 上架 | K110: 否 | L110: 否 | M110: 2023-04-28 00:00:00 | N110: 6 | O110: /products/onepiece-official/gift-26.jpg | Q110: 礼盒 | R110: 航海王卡牌对战简体中文版官方套装。官方商品 ID：26，价格待核。 | T110: onepiece-gift-26

Sheet 火影
A1: 火影 · PIMART
A2: 【大纲 1 / 2】点「1」只显示原盒主行（日常改库存/售价）。点「2」或行号旁「+」展开散包/原箱（有规格的新品写到这一层）。新品：先写规格=原盒，再在下方挂散包、原箱两行。
Q3: ← 规格列：橙=原箱 | 蓝=原盒 | 绿=散包 | 紫=商品类型（日常改库存/销售价即可）
A4: 商品名 | B4: 系列 | C4: 盒型/类型 | D4: 规格 | E4: 销售状态 | F4: 库存 | G4: 销售价(JPY) | H4: 成本价(CNY) | I4: 语言 | J4: 网站状态 | K4: 是否预售 | L4: 首页推荐 | M4: 发售日 | N4: 发货天数 | O4: 图片 | P4: 优先级 | Q4: 原箱库存 | R4: 原箱销售价(JPY) | S4: 原箱建议售价(JPY) | T4: 原箱毛利(JPY) | U4: 原箱毛利率 | V4: 原箱库存金额(JPY) | W4: 原箱价格状态 | X4: 原箱库存状态 | Y4: 原箱调价建议 | Z4: 原盒库存 | AA4: 原盒销售价(JPY) | AB4: 原盒建议售价(JPY) | AC4: 原盒毛利(JPY) | AD4: 原盒毛利率 | AE4: 原盒库存金额(JPY) | AF4: 原盒价格状态 | AG4: 原盒库存状态 | AH4: 原盒调价建议 | AI4: 散包库存 | AJ4: 散包销售价(JPY) | AK4: 散包建议售价(JPY) | AL4: 散包毛利(JPY) | AM4: 散包毛利率 | AN4: 散包库存金额(JPY) | AO4: 散包价格状态 | AP4: 散包库存状态 | AQ4: 散包调价建议 | AR4: 备注 | AS4: 商品ID | AT4: SKU/Slug | AU4: 游戏 | AV4: 商品链接
A5: 单条：点「原盒」那一行【左边行号旁】的 + 展开散包/原箱，点 - 收回
A6: 卡游 / 官方
A8: 系列扩展
A10: 礼盒 / 周边
A12: 其他

Sheet 全量库存
A1: 全量库存 · 汇总
A2: 自动汇总各 IP 分页商品行（不含分组标题）。日常请在宝可梦/海贼王/火影页改库存与售价。
A4: 来源页 | B4: 商品名 | C4: 系列 | D4: 盒型/类型 | E4: 销售状态 | F4: 库存 | G4: 销售价(JPY) | H4: 备注
A5: 宝可梦 | B5: =宝可梦!A5 | C5: =宝可梦!B5 | D5: =宝可梦!C5 | E5: =宝可梦!D5 | F5: =宝可梦!E5 | G5: =宝可梦!G5 | H5: =宝可梦!#REF!
A6: 宝可梦 | B6: =宝可梦!A6 | C6: =宝可梦!B6 | D6: =宝可梦!C6 | E6: =宝可梦!D6 | F6: =宝可梦!E6 | G6: =宝可梦!G6 | H6: =宝可梦!#REF!
A7: 宝可梦 | B7: =宝可梦!A7 | C7: =宝可梦!B7 | D7: =宝可梦!C7 | E7: =宝可梦!D7 | F7: =宝可梦!E7 | G7: =宝可梦!G7 | H7: =宝可梦!#REF!
A8: 宝可梦 | B8: =宝可梦!A8 | C8: =宝可梦!B8 | D8: =宝可梦!C8 | E8: =宝可梦!D8 | F8: =宝可梦!E8 | G8: =宝可梦!G8 | H8: =宝可梦!#REF!
A9: 宝可梦 | B9: =宝可梦!A11 | C9: =宝可梦!B11 | D9: =宝可梦!C11 | E9: =宝可梦!D11 | F9: =宝可梦!E11 | G9: =宝可梦!G11 | H9: =宝可梦!#REF!
A10: 宝可梦 | B10: =宝可梦!A12 | C10: =宝可梦!B12 | D10: =宝可梦!C12 | E10: =宝可梦!D12 | F10: =宝可梦!E12 | G10: =宝可梦!G12 | H10: =宝可梦!#REF!
A11: 宝可梦 | B11: =宝可梦!A13 | C11: =宝可梦!B13 | D11: =宝可梦!C13 | E11: =宝可梦!D13 | F11: =宝可梦!E13 | G11: =宝可梦!G13 | H11: =宝可梦!#REF!
A12: 宝可梦 | B12: =宝可梦!A14 | C12: =宝可梦!B14 | D12: =宝可梦!C14 | E12: =宝可梦!D14 | F12: =宝可梦!E14 | G12: =宝可梦!G14 | H12: =宝可梦!#REF!
A13: 宝可梦 | B13: =宝可梦!A19 | C13: =宝可梦!B19 | D13: =宝可梦!C19 | E13: =宝可梦!D19 | F13: =宝可梦!E19 | G13: =宝可梦!G19 | H13: =宝可梦!#REF!
A14: 宝可梦 | B14: =宝可梦!A20 | C14: =宝可梦!B20 | D14: =宝可梦!C20 | E14: =宝可梦!D20 | F14: =宝可梦!E20 | G14: =宝可梦!G20 | H14: =宝可梦!#REF!
A15: 宝可梦 | B15: =宝可梦!A21 | C15: =宝可梦!B21 | D15: =宝可梦!C21 | E15: =宝可梦!D21 | F15: =宝可梦!E21 | G15: =宝可梦!G21 | H15: =宝可梦!#REF!
A16: 宝可梦 | B16: =宝可梦!A24 | C16: =宝可梦!B24 | D16: =宝可梦!C24 | E16: =宝可梦!D24 | F16: =宝可梦!E24 | G16: =宝可梦!G24 | H16: =宝可梦!#REF!
A17: 宝可梦 | B17: =宝可梦!A25 | C17: =宝可梦!B25 | D17: =宝可梦!C25 | E17: =宝可梦!D25 | F17: =宝可梦!E25 | G17: =宝可梦!G25 | H17: =宝可梦!#REF!
A18: 宝可梦 | B18: =宝可梦!A26 | C18: =宝可梦!B26 | D18: =宝可梦!C26 | E18: =宝可梦!D26 | F18: =宝可梦!E26 | G18: =宝可梦!G26 | H18: =宝可梦!#REF!
A19: 宝可梦 | B19: =宝可梦!A29 | C19: =宝可梦!B29 | D19: =宝可梦!C29 | E19: =宝可梦!D29 | F19: =宝可梦!E29 | G19: =宝可梦!G29 | H19: =宝可梦!#REF!
A20: 宝可梦 | B20: =宝可梦!A30 | C20: =宝可梦!B30 | D20: =宝可梦!C30 | E20: =宝可梦!D30 | F20: =宝可梦!E30 | G20: =宝可梦!G30 | H20: =宝可梦!#REF!
A21: 宝可梦 | B21: =宝可梦!A31 | C21: =宝可梦!B31 | D21: =宝可梦!C31 | E21: =宝可梦!D31 | F21: =宝可梦!E31 | G21: =宝可梦!G31 | H21: =宝可梦!#REF!
A22: 宝可梦 | B22: =宝可梦!A34 | C22: =宝可梦!B34 | D22: =宝可梦!C34 | E22: =宝可梦!D34 | F22: =宝可梦!E34 | G22: =宝可梦!G34 | H22: =宝可梦!#REF!
A23: 宝可梦 | B23: =宝可梦!A35 | C23: =宝可梦!B35 | D23: =宝可梦!C35 | E23: =宝可梦!D35 | F23: =宝可梦!E35 | G23: =宝可梦!G35 | H23: =宝可梦!#REF!
A24: 宝可梦 | B24: =宝可梦!A36 | C24: =宝可梦!B36 | D24: =宝可梦!C36 | E24: =宝可梦!D36 | F24: =宝可梦!E36 | G24: =宝可梦!G36 | H24: =宝可梦!#REF!
A25: 宝可梦 | B25: =宝可梦!A39 | C25: =宝可梦!B39 | D25: =宝可梦!C39 | E25: =宝可梦!D39 | F25: =宝可梦!E39 | G25: =宝可梦!G39 | H25: =宝可梦!#REF!
A26: 宝可梦 | B26: =宝可梦!A40 | C26: =宝可梦!B40 | D26: =宝可梦!C40 | E26: =宝可梦!D40 | F26: =宝可梦!E40 | G26: =宝可梦!G40 | H26: =宝可梦!#REF!
A27: 宝可梦 | B27: =宝可梦!A41 | C27: =宝可梦!B41 | D27: =宝可梦!C41 | E27: =宝可梦!D41 | F27: =宝可梦!E41 | G27: =宝可梦!G41 | H27: =宝可梦!#REF!
A28: 宝可梦 | B28: =宝可梦!A44 | C28: =宝可梦!B44 | D28: =宝可梦!C44 | E28: =宝可梦!D44 | F28: =宝可梦!E44 | G28: =宝可梦!G44 | H28: =宝可梦!#REF!
A29: 宝可梦 | B29: =宝可梦!A45 | C29: =宝可梦!B45 | D29: =宝可梦!C45 | E29: =宝可梦!D45 | F29: =宝可梦!E45 | G29: =宝可梦!G45 | H29: =宝可梦!#REF!
A30: 宝可梦 | B30: =宝可梦!A50 | C30: =宝可梦!B50 | D30: =宝可梦!C50 | E30: =宝可梦!D50 | F30: =宝可梦!E50 | G30: =宝可梦!G50 | H30: =宝可梦!#REF!
A31: 宝可梦 | B31: =宝可梦!A51 | C31: =宝可梦!B51 | D31: =宝可梦!C51 | E31: =宝可梦!D51 | F31: =宝可梦!E51 | G31: =宝可梦!G51 | H31: =宝可梦!#REF!
A32: 宝可梦 | B32: =宝可梦!A54 | C32: =宝可梦!B54 | D32: =宝可梦!C54 | E32: =宝可梦!D54 | F32: =宝可梦!E54 | G32: =宝可梦!G54 | H32: =宝可梦!#REF!
A33: 宝可梦 | B33: =宝可梦!A55 | C33: =宝可梦!B55 | D33: =宝可梦!C55 | E33: =宝可梦!D55 | F33: =宝可梦!E55 | G33: =宝可梦!G55 | H33: =宝可梦!#REF!
A34: 宝可梦 | B34: =宝可梦!A58 | C34: =宝可梦!B58 | D34: =宝可梦!C58 | E34: =宝可梦!D58 | F34: =宝可梦!E58 | G34: =宝可梦!G58 | H34: =宝可梦!#REF!
A35: 宝可梦 | B35: =宝可梦!A59 | C35: =宝可梦!B59 | D35: =宝可梦!C59 | E35: =宝可梦!D59 | F35: =宝可梦!E59 | G35: =宝可梦!G59 | H35: =宝可梦!#REF!
A36: 宝可梦 | B36: =宝可梦!A62 | C36: =宝可梦!B62 | D36: =宝可梦!C62 | E36: =宝可梦!D62 | F36: =宝可梦!E62 | G36: =宝可梦!G62 | H36: =宝可梦!#REF!
A37: 宝可梦 | B37: =宝可梦!A63 | C37: =宝可梦!B63 | D37: =宝可梦!C63 | E37: =宝可梦!D63 | F37: =宝可梦!E63 | G37: =宝可梦!G63 | H37: =宝可梦!#REF!
A38: 宝可梦 | B38: =宝可梦!A66 | C38: =宝可梦!B66 | D38: =宝可梦!C66 | E38: =宝可梦!D66 | F38: =宝可梦!E66 | G38: =宝可梦!G66 | H38: =宝可梦!#REF!
A39: 宝可梦 | B39: =宝可梦!A67 | C39: =宝可梦!B67 | D39: =宝可梦!C67 | E39: =宝可梦!D67 | F39: =宝可梦!E67 | G39: =宝可梦!G67 | H39: =宝可梦!#REF!
A40: 宝可梦 | B40: =宝可梦!A70 | C40: =宝可梦!B70 | D40: =宝可梦!C70 | E40: =宝可梦!D70 | F40: =宝可梦!E70 | G40: =宝可梦!G70 | H40: =宝可梦!#REF!
A41: 宝可梦 | B41: =宝可梦!A71 | C41: =宝可梦!B71 | D41: =宝可梦!C71 | E41: =宝可梦!D71 | F41: =宝可梦!E71 | G41: =宝可梦!G71 | H41: =宝可梦!#REF!
A42: 宝可梦 | B42: =宝可梦!A74 | C42: =宝可梦!B74 | D42: =宝可梦!C74 | E42: =宝可梦!D74 | F42: =宝可梦!E74 | G42: =宝可梦!G74 | H42: =宝可梦!#REF!
A43: 宝可梦 | B43: =宝可梦!A75 | C43: =宝可梦!B75 | D43: =宝可梦!C75 | E43: =宝可梦!D75 | F43: =宝可梦!E75 | G43: =宝可梦!G75 | H43: =宝可梦!#REF!
A44: 宝可梦 | B44: =宝可梦!A78 | C44: =宝可梦!B78 | D44: =宝可梦!C78 | E44: =宝可梦!D78 | F44: =宝可梦!E78 | G44: =宝可梦!G78 | H44: =宝可梦!#REF!
A45: 宝可梦 | B45: =宝可梦!A79 | C45: =宝可梦!B79 | D45: =宝可梦!C79 | E45: =宝可梦!D79 | F45: =宝可梦!E79 | G45: =宝可梦!G79 | H45: =宝可梦!#REF!
A46: 宝可梦 | B46: =宝可梦!A82 | C46: =宝可梦!B82 | D46: =宝可梦!C82 | E46: =宝可梦!D82 | F46: =宝可梦!E82 | G46: =宝可梦!G82 | H46: =宝可梦!#REF!
A47: 宝可梦 | B47: =宝可梦!A83 | C47: =宝可梦!B83 | D47: =宝可梦!C83 | E47: =宝可梦!D83 | F47: =宝可梦!E83 | G47: =宝可梦!G83 | H47: =宝可梦!#REF!
A48: 宝可梦 | B48: =宝可梦!A86 | C48: =宝可梦!B86 | D48: =宝可梦!C86 | E48: =宝可梦!D86 | F48: =宝可梦!E86 | G48: =宝可梦!G86 | H48: =宝可梦!#REF!
A49: 宝可梦 | B49: =宝可梦!A87 | C49: =宝可梦!B87 | D49: =宝可梦!C87 | E49: =宝可梦!D87 | F49: =宝可梦!E87 | G49: =宝可梦!G87 | H49: =宝可梦!#REF!
A50: 宝可梦 | B50: =宝可梦!A88 | C50: =宝可梦!B88 | D50: =宝可梦!C88 | E50: =宝可梦!D88 | F50: =宝可梦!E88 | G50: =宝可梦!G88 | H50: =宝可梦!#REF!
A51: 宝可梦 | B51: =宝可梦!A89 | C51: =宝可梦!B89 | D51: =宝可梦!C89 | E51: =宝可梦!D89 | F51: =宝可梦!E89 | G51: =宝可梦!G89 | H51: =宝可梦!#REF!
A52: 宝可梦 | B52: =宝可梦!A90 | C52: =宝可梦!B90 | D52: =宝可梦!C90 | E52: =宝可梦!D90 | F52: =宝可梦!E90 | G52: =宝可梦!G90 | H52: =宝可梦!#REF!
A53: 宝可梦 | B53: =宝可梦!A91 | C53: =宝可梦!B91 | D53: =宝可梦!C91 | E53: =宝可梦!D91 | F53: =宝可梦!E91 | G53: =宝可梦!G91 | H53: =宝可梦!#REF!
A54: 宝可梦 | B54: =宝可梦!A92 | C54: =宝可梦!B92 | D54: =宝可梦!C92 | E54: =宝可梦!D92 | F54: =宝可梦!E92 | G54: =宝可梦!G92 | H54: =宝可梦!#REF!
A55: 宝可梦 | B55: =宝可梦!A93 | C55: =宝可梦!B93 | D55: =宝可梦!C93 | E55: =宝可梦!D93 | F55: =宝可梦!E93 | G55: =宝可梦!G93 | H55: =宝可梦!#REF!
A56: 宝可梦 | B56: =宝可梦!A94 | C56: =宝可梦!B94 | D56: =宝可梦!C94 | E56: =宝可梦!D94 | F56: =宝可梦!E94 | G56: =宝可梦!G94 | H56: =宝可梦!#REF!
A57: 宝可梦 | B57: =宝可梦!A95 | C57: =宝可梦!B95 | D57: =宝可梦!C95 | E57: =宝可梦!D95 | F57: =宝可梦!E95 | G57: =宝可梦!G95 | H57: =宝可梦!#REF!
A58: 宝可梦 | B58: =宝可梦!A96 | C58: =宝可梦!B96 | D58: =宝可梦!C96 | E58: =宝可梦!D96 | F58: =宝可梦!E96 | G58: =宝可梦!G96 | H58: =宝可梦!#REF!
A59: 宝可梦 | B59: =宝可梦!A100 | C59: =宝可梦!B100 | D59: =宝可梦!C100 | E59: =宝可梦!D100 | F59: =宝可梦!E100 | G59: =宝可梦!G100 | H59: =宝可梦!#REF!
A60: 宝可梦 | B60: =宝可梦!A101 | C60: =宝可梦!B101 | D60: =宝可梦!C101 | E60: =宝可梦!D101 | F60: =宝可梦!E101 | G60: =宝可梦!G101 | H60: =宝可梦!#REF!
A61: 宝可梦 | B61: =宝可梦!A102 | C61: =宝可梦!B102 | D61: =宝可梦!C102 | E61: =宝可梦!D102 | F61: =宝可梦!E102 | G61: =宝可梦!G102 | H61: =宝可梦!#REF!
A62: 宝可梦 | B62: =宝可梦!A103 | C62: =宝可梦!B103 | D62: =宝可梦!C103 | E62: =宝可梦!D103 | F62: =宝可梦!E103 | G62: =宝可梦!G103 | H62: =宝可梦!#REF!
A63: 宝可梦 | B63: =宝可梦!A104 | C63: =宝可梦!B104 | D63: =宝可梦!C104 | E63: =宝可梦!D104 | F63: =宝可梦!E104 | G63: =宝可梦!G104 | H63: =宝可梦!#REF!
A64: 宝可梦 | B64: =宝可梦!A107 | C64: =宝可梦!B107 | D64: =宝可梦!C107 | E64: =宝可梦!D107 | F64: =宝可梦!E107 | G64: =宝可梦!G107 | H64: =宝可梦!#REF!
A65: 宝可梦 | B65: =宝可梦!A108 | C65: =宝可梦!B108 | D65: =宝可梦!C108 | E65: =宝可梦!D108 | F65: =宝可梦!E108 | G65: =宝可梦!G108 | H65: =宝可梦!#REF!
A66: 宝可梦 | B66: =宝可梦!A109 | C66: =宝可梦!B109 | D66: =宝可梦!C109 | E66: =宝可梦!D109 | F66: =宝可梦!E109 | G66: =宝可梦!G109 | H66: =宝可梦!#REF!
A67: 宝可梦 | B67: =宝可梦!A110 | C67: =宝可梦!B110 | D67: =宝可梦!C110 | E67: =宝可梦!D110 | F67: =宝可梦!E110 | G67: =宝可梦!G110 | H67: =宝可梦!#REF!
A68: 宝可梦 | B68: =宝可梦!A111 | C68: =宝可梦!B111 | D68: =宝可梦!C111 | E68: =宝可梦!D111 | F68: =宝可梦!E111 | G68: =宝可梦!G111 | H68: =宝可梦!#REF!
A69: 宝可梦 | B69: =宝可梦!A112 | C69: =宝可梦!B112 | D69: =宝可梦!C112 | E69: =宝可梦!D112 | F69: =宝可梦!E112 | G69: =宝可梦!G112 | H69: =宝可梦!#REF!
A70: 宝可梦 | B70: =宝可梦!A113 | C70: =宝可梦!B113 | D70: =宝可梦!C113 | E70: =宝可梦!D113 | F70: =宝可梦!E113 | G70: =宝可梦!G113 | H70: =宝可梦!#REF!
A71: 宝可梦 | B71: =宝可梦!A114 | C71: =宝可梦!B114 | D71: =宝可梦!C114 | E71: =宝可梦!D114 | F71: =宝可梦!E114 | G71: =宝可梦!G114 | H71: =宝可梦!#REF!
A72: 宝可梦 | B72: =宝可梦!A115 | C72: =宝可梦!B115 | D72: =宝可梦!C115 | E72: =宝可梦!D115 | F72: =宝可梦!E115 | G72: =宝可梦!G115 | H72: =宝可梦!#REF!
A73: 宝可梦 | B73: =宝可梦!A116 | C73: =宝可梦!B116 | D73: =宝可梦!C116 | E73: =宝可梦!D116 | F73: =宝可梦!E116 | G73: =宝可梦!G116 | H73: =宝可梦!#REF!
A74: 海贼王 | B74: =海贼王!A5 | C74: =海贼王!B5 | D74: =海贼王!C5 | E74: =海贼王!D5 | F74: =海贼王!E5 | G74: =海贼王!G5 | H74: =海贼王!#REF!
A75: 海贼王 | B75: =海贼王!A6 | C75: =海贼王!B6 | D75: =海贼王!C6 | E75: =海贼王!D6 | F75: =海贼王!E6 | G75: =海贼王!G6 | H75: =海贼王!#REF!
A76: 海贼王 | B76: =海贼王!A7 | C76: =海贼王!B7 | D76: =海贼王!C7 | E76: =海贼王!D7 | F76: =海贼王!E7 | G76: =海贼王!G7 | H76: =海贼王!#REF!
A77: 海贼王 | B77: =海贼王!A8 | C77: =海贼王!B8 | D77: =海贼王!C8 | E77: =海贼王!D8 | F77: =海贼王!E8 | G77: =海贼王!G8 | H77: =海贼王!#REF!
A78: 海贼王 | B78: =海贼王!A9 | C78: =海贼王!B9 | D78: =海贼王!C9 | E78: =海贼王!D9 | F78: =海贼王!E9 | G78: =海贼王!G9 | H78: =海贼王!#REF!
A79: 海贼王 | B79: =海贼王!A10 | C79: =海贼王!B10 | D79: =海贼王!C10 | E79: =海贼王!D10 | F79: =海贼王!E10 | G79: =海贼王!G10 | H79: =海贼王!#REF!
A80: 海贼王 | B80: =海贼王!A11 | C80: =海贼王!B11 | D80: =海贼王!C11 | E80: =海贼王!D11 | F80: =海贼王!E11 | G80: =海贼王!G11 | H80: =海贼王!#REF!
A81: 海贼王 | B81: =海贼王!A12 | C81: =海贼王!B12 | D81: =海贼王!C12 | E81: =海贼王!D12 | F81: =海贼王!E12 | G81: =海贼王!G12 | H81: =海贼王!#REF!
A82: 海贼王 | B82: =海贼王!A13 | C82: =海贼王!B13 | D82: =海贼王!C13 | E82: =海贼王!D13 | F82: =海贼王!E13 | G82: =海贼王!G13 | H82: =海贼王!#REF!
A83: 海贼王 | B83: =海贼王!A14 | C83: =海贼王!B14 | D83: =海贼王!C14 | E83: =海贼王!D14 | F83: =海贼王!E14 | G83: =海贼王!G14 | H83: =海贼王!#REF!
A84: 海贼王 | B84: =海贼王!A15 | C84: =海贼王!B15 | D84: =海贼王!C15 | E84: =海贼王!D15 | F84: =海贼王!E15 | G84: =海贼王!G15 | H84: =海贼王!#REF!
A85: 海贼王 | B85: =海贼王!A16 | C85: =海贼王!B16 | D85: =海贼王!C16 | E85: =海贼王!D16 | F85: =海贼王!E16 | G85: =海贼王!G16 | H85: =海贼王!#REF!
... A89: 海贼王 | B89: =海贼王!A20 | C89: =海贼王!B20 | D89: =海贼王!C20 | E89: =海贼王!D20 | F89: =海贼王!E20 | G89: =海贼王!G20 | H89: =海贼王!#REF!
A90: 海贼王 | B90: =海贼王!A23 | C90: =海贼王!B23 | D90: =海贼王!C23 | E90: =海贼王!D23 | F90: =海贼王!E23 | G90: =海贼王!G23 | H90: =海贼王!#REF!
A91: 海贼王 | B91: =海贼王!A24 | C91: =海贼王!B24 | D91: =海贼王!C24 | E91: =海贼王!D24 | F91: =海贼王!E24 | G91: =海贼王!G24 | H91: =海贼王!#REF!
A92: 海贼王 | B92: =海贼王!A25 | C92: =海贼王!B25 | D92: =海贼王!C25 | E92: =海贼王!D25 | F92: =海贼王!E25 | G92: =海贼王!G25 | H92: =海贼王!#REF!
A93: 海贼王 | B93: =海贼王!A26 | C93: =海贼王!B26 | D93: =海贼王!C26 | E93: =海贼王!D26 | F93: =海贼王!E26 | G93: =海贼王!G26 | H93: =海贼王!#REF!
A94: 海贼王 | B94: =海贼王!A29 | C94: =海贼王!B29 | D94: =海贼王!C29 | E94: =海贼王!D29 | F94: =海贼王!E29 | G94: =海贼王!G29 | H94: =海贼王!#REF!
A95: 海贼王 | B95: =海贼王!A30 | C95: =海贼王!B30 | D95: =海贼王!C30 | E95: =海贼王!D30 | F95: =海贼王!E30 | G95: =海贼王!G30 | H95: =海贼王!#REF!
A96: 海贼王 | B96: =海贼王!A33 | C96: =海贼王!B33 | D96: =海贼王!C33 | E96: =海贼王!D33 | F96: =海贼王!E33 | G96: =海贼王!G33 | H96: =海贼王!#REF!
A97: 海贼王 | B97: =海贼王!A34 | C97: =海贼王!B34 | D97: =海贼王!C34 | E97: =海贼王!D34 | F97: =海贼王!E34 | G97: =海贼王!G34 | H97: =海贼王!#REF!
A98: 海贼王 | B98: =海贼王!A35 | C98: =海贼王!B35 | D98: =海贼王!C35 | E98: =海贼王!D35 | F98: =海贼王!E35 | G98: =海贼王!G35 | H98: =海贼王!#REF!
A99: 海贼王 | B99: =海贼王!A36 | C99: =海贼王!B36 | D99: =海贼王!C36 | E99: =海贼王!D36 | F99: =海贼王!E36 | G99: =海贼王!G36 | H99: =海贼王!#REF!
A100: 海贼王 | B100: =海贼王!A37 | C100: =海贼王!B37 | D100: =海贼王!C37 | E100: =海贼王!D37 | F100: =海贼王!E37 | G100: =海贼王!G37 | H100: =海贼王!#REF!
A101: 海贼王 | B101: =海贼王!A38 | C101: =海贼王!B38 | D101: =海贼王!C38 | E101: =海贼王!D38 | F101: =海贼王!E38 | G101: =海贼王!G38 | H101: =海贼王!#REF!
A102: 海贼王 | B102: =海贼王!A39 | C102: =海贼王!B39 | D102: =海贼王!C39 | E102: =海贼王!D39 | F102: =海贼王!E39 | G102: =海贼王!G39 | H102: =海贼王!#REF!
A103: 海贼王 | B103: =海贼王!A40 | C103: =海贼王!B40 | D103: =海贼王!C40 | E103: =海贼王!D40 | F103: =海贼王!E40 | G103: =海贼王!G40 | H103: =海贼王!#REF!
A104: 海贼王 | B104: =海贼王!A41 | C104: =海贼王!B41 | D104: =海贼王!C41 | E104: =海贼王!D41 | F104: =海贼王!E41 | G104: =海贼王!G41 | H104: =海贼王!#REF!
...

Sheet 售罄与未上架
A1: 销售状态 | B1: 商品名 | C1: 系列 | D1: 盒型 | E1: 网站状态 | F1: 库存 | G1: 销售价(JPY) | H1: Obsidian状态 | I1: 来源 | J1: 备注
A2: 售罄 | B2: 宝石包第二弹 BOX（简中） | C2: 宝石包 | D2: 宝石包 | E2: 上架 | F2: 0 | G2: 8500 | I2: 网站公开商品页 + Obsidian | J2: 简中宝可梦 宝石包 第二弹（CBB2C）原盒，2025年5月16日发售，每盒15包，每包4张全闪。
A3: 售罄 | B3: 宝石包第三弹 BOX（简中） | C3: 宝石包 | D3: 宝石包 | E3: 上架 | F3: 0 | G3: 8000 | I3: 网站公开商品页 + Obsidian | J3: 简中宝可梦 宝石包 第三弹（CBB3C）原盒，2025年9月26日发售，每盒15包，每包4张全闪。
A4: 售罄 | B4: 宝石包第四弹 BOX（简中） | C4: 宝石包 | D4: 宝石包 | E4: 上架 | F4: 0 | G4: 7600 | I4: 网站公开商品页 + Obsidian | J4: 简中宝可梦 宝石包 第四弹（CBB4C）原盒，2026年2月6日发售，每盒15包，每包4张全闪。
A5: 售罄 | B5: 宝石包第一弹 BOX（简中） | C5: 宝石包 | D5: 宝石包 | E5: 上架 | F5: 0 | G5: 9000 | I5: 网站公开商品页 + Obsidian | J5: 简中宝可梦 宝石包 第一弹（CBB1C）原盒，2025年1月17日发售，每盒15包，每包4张全闪。
A6: 售罄 | B6: 极巨攻防 BOX（简中） | C6: 剑&盾 CS1.5 | D6: 瘦盒 | E6: 上架 | F6: 0 | G6: 3800 | I6: 网站公开商品页 + Obsidian | J6: 简中宝可梦 剑&盾 强化包 极巨攻防（CS1.5C），6张/包×20包/盒。
A7: 售罄 | B7: 极巨争锋 雷 BOX（简中） | C7: 剑&盾 CS1a | D7: 肥盒 | E7: 上架 | F7: 0 | G7: 4800 | I7: 网站公开商品页 + Obsidian | J7: 简中宝可梦 剑&盾 极巨争锋 雷（CS1aC），2023年5月19日发售，5张/包×30包/盒。
A8: 售罄 | B8: 极巨争锋 焰 BOX（简中） | C8: 剑&盾 CS1b | D8: 肥盒 | E8: 上架 | F8: 0 | G8: 4800 | I8: 网站公开商品页 + Obsidian | J8: 简中宝可梦 剑&盾 极巨争锋 焰（CS1bC），2023年5月19日发售，5张/包×30包/盒。
A9: 售罄 | B9: 璀璨反击 BOX（简中） | C9: 剑&盾 CS2.5 | D9: 瘦盒 | E9: 上架 | F9: 0 | G9: 3800 | I9: 网站公开商品页 + Obsidian | J9: 简中宝可梦 剑&盾 强化包 璀璨反击（CS2.5C），6张/包×20包/盒。
A10: 售罄 | B10: 浓墨重彩 黎 BOX（简中） | C10: 剑&盾 CS2a | D10: 肥盒 | E10: 上架 | F10: 0 | G10: 4800 | I10: 网站公开商品页 + Obsidian | J10: 简中宝可梦 剑&盾 浓墨重彩 黎（CS2aC），2023年8月18日发售，5张/包×30包/盒。
A11: 售罄 | B11: 浓墨重彩 靛 BOX（简中） | C11: 剑&盾 CS2b | D11: 肥盒 | E11: 上架 | F11: 0 | G11: 4800 | I11: 网站公开商品页 + Obsidian | J11: 简中宝可梦 剑&盾 浓墨重彩 靛（CS2bC），2023年8月18日发售，5张/包×30包/盒。
A12: 售罄 | B12: 怒炎灼天 BOX（简中） | C12: 剑&盾 CS3.5 | D12: 瘦盒 | E12: 上架 | F12: 0 | G12: 3800 | I12: 网站公开商品页 + Obsidian | J12: 简中宝可梦 剑&盾 强化包 怒炎灼天（CS3.5C），6张/包×20包/盒。
A13: 售罄 | B13: 洪荒演武 茂 BOX（简中） | C13: 剑&盾 CS3a | D13: 肥盒 | E13: 上架 | F13: 0 | G13: 5000 | I13: 网站公开商品页 + Obsidian | J13: 简中宝可梦 剑&盾 洪荒演武 茂（CS3aC），2023年11月17日发售，5张/包×30包/盒。
... A35: 售罄 | B35: 璀璨诡幻 BOX（简中） | C35: 朱・紫 CSV8c | D35: 肥盒 | E35: 上架 | F35: 0 | G35: 6000 | I35: 网站公开商品页 + Obsidian | J35: 简中宝可梦 朱&紫 璀璨诡幻（CSV8C）原盒，2026年3月13日发售，每盒30包，每包5张。
A36: 未上架 | B36: 朱紫 三连击 | C36: 宝可梦卡牌 | D36: booster_box | E36: 草稿 | F36: 0 | H36: draft | I36: Obsidian 产品笔记 | J36: 未在网站公开 Pokemon 列表中命中：C:\Users\33092\Desktop\obsi\KANDA\KKCARD OS\Products\JP\SV1A-トリプレットビート.md

Sheet 图片库
A1: 总表行号 | B1: 商品名 | C1: 系列/编号 | D1: 匹配状态 | E1: pokemon.cn标题 | F1: 本地文件名 | G1: 图片相对路径(网站) | H1: 来源URL | I1: 备注
A2: 6 | B2: 补充包 共逐荣光 瘦盒 BOX（简中） | C2: 朱・紫 CSV10c | D2: 已备份 | E2: 补充包 共逐荣光 瘦盒 BOX（简中） | F2: csv10c-slim.png | G2: /products/csv10c-slim.png | I2: DB status=上架
A3: 9 | B3: 补充包 共逐荣光 肥盒 BOX（简中） | C3: 朱・紫 CSV10c | D3: 已备份 | E3: 补充包 共逐荣光 肥盒 BOX（简中） | F3: csv10c-fat.png | G3: /products/csv10c-fat.png | I3: DB status=上架
A4: 13 | B4: 补充包 星彩晶璃 瘦盒 BOX（简中） | C4: 朱・紫 CSV9c | D4: 已备份 | E4: 补充包 星彩晶璃 瘦盒 BOX（简中） | F4: csv9c-slim.png | G4: /products/csv9c-slim.png | I4: DB status=上架
A5: 16 | B5: 补充包 星彩晶璃 肥盒 BOX（简中） | C5: 朱・紫 CSV9c | D5: 已备份 | E5: 补充包 星彩晶璃 肥盒 BOX（简中） | F5: csv9c-fat.png | G5: /products/csv9c-fat.png | I5: DB status=上架
A6: 20 | B6: 补充包 璀璨诡幻 瘦盒 BOX（简中） | C6: 朱・紫 CSV8c | D6: 已备份 | E6: 补充包 璀璨诡幻 瘦盒 BOX（简中） | F6: csv8c-slim.png | G6: /products/csv8c-slim.png | I6: DB status=上架
A7: 23 | B7: 补充包 璀璨诡幻 肥盒 BOX（简中） | C7: 朱・紫 CSV8c | D7: 已备份 | E7: 补充包 璀璨诡幻 肥盒 BOX（简中） | F7: csv8c-fat.png | G7: /products/csv8c-fat.png | I7: DB status=上架
A8: 27 | B8: 补充包 利刃猛醒 瘦盒 BOX（简中） | C8: 朱・紫 CSV7c | D8: 已备份 | E8: 补充包 利刃猛醒 瘦盒 BOX（简中） | F8: csv7c-slim.png | G8: /products/csv7c-slim.png | I8: DB status=上架
A9: 30 | B9: 补充包 利刃猛醒 肥盒 BOX（简中） | C9: 朱・紫 CSV7c | D9: 已备份 | E9: 补充包 利刃猛醒 肥盒 BOX（简中） | F9: csv7c-fat.png | G9: /products/csv7c-fat.png | I9: DB status=上架
A10: 34 | B10: 补充包 真实玄虚 瘦盒 BOX（简中） | C10: 朱・紫 CSV6c | D10: 已备份 | E10: 补充包 真实玄虚 瘦盒 BOX（简中） | F10: csv6c-slim.png | G10: /products/csv6c-slim.png | I10: DB status=上架
A11: 37 | B11: 补充包 真实玄虚 肥盒 BOX（简中） | C11: 朱・紫 CSV6c | D11: 已备份 | E11: 补充包 真实玄虚 肥盒 BOX（简中） | F11: csv6c-fat.png | G11: /products/csv6c-fat.png | I11: DB status=上架
A12: 41 | B12: 补充包 黑晶炽诚 瘦盒 BOX（简中） | C12: 朱・紫 CSV5c | D12: 已备份 | E12: 补充包 黑晶炽诚 瘦盒 BOX（简中） | F12: csv5c-slim.png | G12: /products/csv5c-slim.png | I12: DB status=上架
A13: 44 | B13: 补充包 黑晶炽诚 肥盒 BOX（简中） | C13: 朱・紫 CSV5c | D13: 已备份 | E13: 补充包 黑晶炽诚 肥盒 BOX（简中） | F13: csv5c-fat.png | G13: /products/csv5c-fat.png | I13: DB status=上架
... A152: 53 | B152: OPC-01 冒险的黎明 原箱（简中） | C152: OPC-01 | D152: 已备份 | E152: OPC-01 冒险的黎明 原箱（简中） | F152: opc-01-pack.png | G152: /products/onepiece-official/opc-01-pack.png | I152: DB status=上架
A153: 55 | B153: EB 特别补充包 | D153: 已备份 | E153: EB 特别补充包 | F153: placeholder.svg | G153: /products/placeholder.svg | I153: DB status=下架
A154: 56 | B154: EBC-04 艾格赫德危机 原盒（简中） | C154: EBC-04 | D154: 已备份 | E154: EBC-04 艾格赫德危机 原盒（简中） | F154: ebc-04-pack.png | G154: /products/onepiece-official/ebc-04-pack.png | I154: DB status=上架
A155: 57 | B155: EBC-04 艾格赫德危机 散包（简中） | C155: EBC-04 | D155: 已备份 | E155: EBC-04 艾格赫德危机 散包（简中） | F155: ebc-04-pack.png | G155: /products/onepiece-official/ebc-04-pack.png | I155: DB status=上架
A156: 58 | B156: EBC-04 艾格赫德危机 原箱（简中） | C156: EBC-04 | D156: 已备份 | E156: EBC-04 艾格赫德危机 原箱（简中） | F156: ebc-04-pack.png | G156: /products/onepiece-official/ebc-04-pack.png | I156: DB status=上架
A157: 65 | B157: EB-01 特别补充包 纪念收藏合集 原盒（简中） | C157: EB-01 | D157: 已备份 | E157: EB-01 特别补充包 纪念收藏合集 原盒（简中） | F157: ebc-01-pack.png | G157: /products/onepiece-official/ebc-01-pack.png | I157: DB status=上架
A158: 66 | B158: PRB 豪华补充包 / 典藏包 | D158: 已备份 | E158: PRB 豪华补充包 / 典藏包 | F158: placeholder.svg | G158: /products/placeholder.svg | I158: DB status=下架
A159: 67 | B159: PRBC-02 历代典藏合集 Vol.2 原盒（简中） | C159: PRBC-02 | D159: 已备份 | E159: PRBC-02 历代典藏合集 Vol.2 原盒（简中） | F159: prbc-02-pack.png | G159: /products/onepiece-official/prbc-02-pack.png | I159: DB status=上架
A160: 68 | B160: PRBC-02 历代典藏合集 Vol.2 散包（简中） | C160: PRBC-02 | D160: 已备份 | E160: PRBC-02 历代典藏合集 Vol.2 散包（简中） | F160: prbc-02-pack.png | G160: /products/onepiece-official/prbc-02-pack.png | I160: DB status=上架
A161: 69 | B161: PRBC-02 历代典藏合集 Vol.2 原箱（简中） | C161: PRBC-02 | D161: 已备份 | E161: PRBC-02 历代典藏合集 Vol.2 原箱（简中） | F161: prbc-02-pack.png | G161: /products/onepiece-official/prbc-02-pack.png | I161: DB status=上架
A162: 70 | B162: PRBC-01 历代典藏合集 原盒（简中） | C162: PRBC-01 | D162: 已备份 | E162: PRBC-01 历代典藏合集 原盒（简中） | F162: prbc-01-pack.png | G162: /products/onepiece-official/prbc-01-pack.png | I162: DB status=上架
A163: 71 | B163: PRBC-01 历代典藏合集 散包（简中） | C163: PRBC-01 | D163: 已备份 | E163: PRBC-01 历代典藏合集 散包（简中） | F163: prbc-01-pack.png | G163: /products/onepiece-official/prbc-01-pack.png | I163: DB status=上架
A164: 72 | B164: PRBC-01 历代典藏合集 原箱（简中） | C164: PRBC-01 | D164: 已备份 | E164: PRBC-01 历代典藏合集 原箱（简中） | F164: prbc-01-pack.png | G164: /products/onepiece-official/prbc-01-pack.png | I164: DB status=上架
A165: 75 | B165: 基本卡组 对战进阶套组2026（官方名称，简中定价待官方公布） | C165: STC-31~36 | D165: 已备份 | E165: 基本卡组 对战进阶套组2026（官方名称，简中定价待官方公布） | F165: stc-31-36-decks.png | G165: /products/onepiece-official/stc-31-36-decks.png | I165: DB status=上架
A166: 76 | B166: 基本卡组 艾格赫德（官方名称，简中定价待官方公布） | C166: STC-29 | D166: 已备份 | E166: 基本卡组 艾格赫德（官方名称，简中定价待官方公布） | F166: stc-29-deck.png | G166: /products/onepiece-official/stc-29-deck.png | I166: DB status=上架
A167: 77 | B167: 基本卡组 对战进阶套组2025（官方名称，简中定价待官方公布） | C167: STC-23~28 | D167: 已备份 | E167: 基本卡组 对战进阶套组2025（官方名称，简中定价待官方公布） | F167: stc-23-28-decks.png | G167: /products/onepiece-official/stc-23-28-decks.png | I167: DB status=上架
A168: 78 | B168: 基本卡组 两年后再出发（官方名称，简中定价待官方公布） | C168: STC-14 | D168: 已备份 | E168: 基本卡组 两年后再出发（官方名称，简中定价待官方公布） | F168: stc-14-deck.png | G168: /products/onepiece-official/stc-14-deck.png | I168: DB status=上架
A169: 79 | B169: 究极进阶卡组 奇迹的再会（官方名称，简中定价待官方公布） | C169: STC-13 | D169: 已备份 | E169: 究极进阶卡组 奇迹的再会（官方名称，简中定价待官方公布） | F169: stc-13-deck.png | G169: /products/onepiece-official/stc-13-deck.png | I169: DB status=上架
A170: 80 | B170: 基本卡组 佐罗＆山智（官方名称，简中定价待官方公布） | C170: STC-12 | D170: 已备份 | E170: 基本卡组 佐罗＆山智（官方名称，简中定价待官方公布） | F170: stc-12-deck.png | G170: /products/onepiece-official/stc-12-deck.png | I170: DB status=上架
... A198: 110 | B198: 航海王卡牌对战 对战桌垫+卡牌盒套装 -25周年版- （简中） | C198: 航海王礼盒 | D198: 已备份 | E198: 航海王卡牌对战 对战桌垫+卡牌盒套装 -25周年版- （简中） | F198: gift-26.jpg | G198: /products/onepiece-official/gift-26.jpg | I198: DB status=上架

Sheet 出入库记录
A1: 日期 | B1: SKU/Slug | C1: 商品名 | D1: 操作类型 | E1: 数量 | F1: 单价(JPY) | G1: 金额(JPY) | H1: 平台/渠道 | I1: 订单/单号 | J1: 备注
